{
    "T0859": {
        "total": 1,
        "pages": {
            "juans/001.xhtml": 1
        },
        "sentences": {
            "juans/001.xhtml": [
                "，塗香，復開座位，覆請已了，供養法如前。又復內院中央一院主，"
            ]
        }
    },
    "T0866": {
        "total": 2,
        "pages": {
            "juans/004.xhtml": 2
        },
        "sentences": {
            "juans/004.xhtml": [
                "。「復以金剛讚歎密語作四種密供養法已，誦此伽他曰：「『金剛薩",
                "以金剛舞合掌及金剛戲笑等作密供養法。「次應手執香花供養外壇聖"
            ]
        }
    },
    "T0868": {
        "total": 1,
        "pages": {
            "juans/002.xhtml": 1
        },
        "sentences": {
            "juans/002.xhtml": [
                ")「復次，金剛手！我今已說內供養法，皆是有相月輪等觀，次當演"
            ]
        }
    },
    "T0869": {
        "total": 2,
        "pages": {
            "juans/001.xhtml": 2
        },
        "sentences": {
            "juans/001.xhtml": [
                "入曼茶羅法，為弟子說受十六大供養法，說四種祕密供養法。第五說"
            ]
        }
    },
    "T0871": {
        "total": 2,
        "pages": {
            "juans/001.xhtml": 2
        },
        "sentences": {
            "juans/001.xhtml": [
                "悅安樂，由斯供養。次入五如來供養法，即入毘盧遮那佛觀，結遍照",
                "言，即入塵剎佛海，運心廣大。供養法事既畢，則從前羯磨三十七尊"
            ]
        }
    },
    "T0875": {
        "total": 1,
        "pages": {
            "juans/001.xhtml": 1
        },
        "sentences": {
            "juans/001.xhtml": [
                "置頂上，誦oṃ字二十一遍，是供養法也。次結根本印，念誦根本真"
            ]
        }
    },
    "T0882": {
        "total": 11,
        "pages": {
            "juans/025.xhtml": 1,
            "juans/027.xhtml": 5,
            "juans/028.xhtml": 5
        },
        "sentences": {
            "juans/025.xhtml": [
                "由斯獲得大灌頂。「此佛所說佛供養法門。「如上是為諸部真實誓誡"
            ],
            "juans/027.xhtml": [
                "妙愛事，奉獻供養佛世尊，即得供養法成就。「此佛所說覺智法門。",
                "能知者，依法觀想於佛身，即得供養法成就。「此佛所說覺智法門。",
                "密供養，觀想降三世聖尊，即得供養法成就。「此佛所說金剛祕密法",
                "妙供養，調伏世間印契成，即得供養法成就。「此佛所說觀自在法門",
                "妙供養，一切義成法相應，即得供養法成就。「此佛所說金剛藏法門"
            ],
            "juans/028.xhtml": [
                "有情樂，金剛薩埵等持門，即得供養法成就。「此佛所說妙欲法門。",
                "作利益，金剛降三世法儀，即得供養法成就。「此佛所說金剛手法門",
                "勝妙樂，調伏世間妙相門，即得供養法成就。「此佛所說金剛愛法門",
                "大財利，一切義成妙相門，即得供養法成就。「此佛所說一切義成就",
                "來部施作事業成就教理：「祕密供養法相應，金剛薩埵三摩地，隨所"
            ]
        }
    },
    "T0883": {
        "total": 3,
        "pages": {
            "juans/003.xhtml": 1,
            "juans/004.xhtml": 2
        },
        "sentences": {
            "juans/003.xhtml": [
                "諸如來。行人復作金剛旋舞祕密供養法，隨應持誦一年，功行成已，"
            ],
            "juans/004.xhtml": [
                "剛灌頂。作是灌頂時，所有本部供養法、本部入壇印、及拋華等事皆",
                "就？云何祕密供養事、及彼金剛供養法、香華燈塗供養儀？是中隨應"
            ]
        }
    },
    "T0884": {
        "total": 2,
        "pages": {
            "juans/003.xhtml": 2
        },
        "sentences": {
            "juans/003.xhtml": [
                "就故得無盡樂。「復次當知祕密供養法者，是即觀自在菩薩三摩地門",
                "諸如來！諸佛大智無有上；祕密供養法相應，利益眾生作成就。金剛"
            ]
        }
    },
    "T0885": {
        "total": 6,
        "pages": {
            "juans/002.xhtml": 3,
            "juans/006.xhtml": 3
        },
        "sentences": {
            "juans/002.xhtml": [
                "三乘共宣說，佛大樂清淨，願說供養法。菩提心廣大，善轉妙法輪，",
                "菩薩摩訶薩，受佛勸請已，即說供養法：「遍一切虛空，現廣大字相",
                "，諸佛出生法，供養諸如來。彼供養法者，住身心平等，離著而無礙"
            ],
            "juans/006.xhtml": [
                "身語心業宣說一切如來最上三業供養法：「五種供養法，作最勝供養，",
                "又復以自身語心業宣說三業祕密供養法：「於二處相應，當受彼甘露"
            ]
        }
    },
    "T0887": {
        "total": 1,
        "pages": {
            "juans/003.xhtml": 1
        },
        "sentences": {
            "juans/003.xhtml": [
                "於四門。五法一切想具足，祕密供養法相應，中心想現妙蓮華，周匝"
            ]
        }
    },
    "T0893a": {
        "total": 3,
        "pages": {
            "juans/002.xhtml": 1,
            "juans/003.xhtml": 2
        },
        "sentences": {
            "juans/002.xhtml": [
                "食亦增威力。如上所說念誦護摩供養法則，亦復能令增加威力。蘇悉"
            ],
            "juans/003.xhtml": [
                "外置本部能辦諸事，諸餘外院及供養法皆如前說。此是金剛部補闕之",
                "供養，如於念誦及於曼荼羅所說供養法，此亦如是應作，若於淨室中"
            ]
        }
    },
    "T0893b": {
        "total": 2,
        "pages": {
            "juans/002.xhtml": 1,
            "juans/003.xhtml": 1
        },
        "sentences": {
            "juans/002.xhtml": [
                "食亦增威力。如上所說念誦護摩供養法則，亦復能令增加威力。蘇悉"
            ],
            "juans/003.xhtml": [
                "外置本部能辦諸事。諸餘外院及供養法皆如前說。此是金剛部補闕之"
            ]
        }
    },
    "T0893c": {
        "total": 2,
        "pages": {
            "juans/002.xhtml": 1,
            "juans/003.xhtml": 1
        },
        "sentences": {
            "juans/002.xhtml": [
                "外置本部能辨諸事，諸餘外院及供養法皆如前說，此是金剛部補闕之"
            ],
            "juans/003.xhtml": [
                "食亦增威力。如上所說念誦護摩供養法則亦復能令增加威力。蘇悉地"
            ]
        }
    },
    "T0894a": {
        "total": 10,
        "pages": {
            "juans/001.xhtml": 6,
            "juans/002.xhtml": 2,
            "juans/003.xhtml": 2
        },
        "sentences": {
            "juans/001.xhtml": [
                "No.894蘇悉地羯羅供養法卷上大唐中印度三藏善無畏譯歸命諸",
                "次獻塗香花、燒香及飲食、燃燈供養法；真言并手印，運心供養法；",
                "三部光澤手印)。◎蘇悉地羯羅供養法卷上丹藏即云「蘇悉地羯羅經",
                "丹藏之經，國、宋藏中始終皆無供養法者，丹藏亦於感函有之，委尋",
                "善無畏譯只有三經一法，而無此供養法。今以目錄雖無，詳其文義，"
            ],
            "juans/002.xhtml": [
                "蘇悉地羯羅供養法卷中(通三部次第)大唐中印度三藏善無畏譯◎次",
                "二合)莎訶(去)」蘇悉地羯羅供養法卷中"
            ],
            "juans/003.xhtml": [
                "蘇悉地羯羅供養法卷下大唐中印度三藏善無畏譯於佛部中其線白色、",
                "沐浴尊容及以舍利。蘇悉地羯羅供養法卷下"
            ]
        }
    },
    "T0894b": {
        "total": 6,
        "pages": {
            "juans/001.xhtml": 4,
            "juans/002.xhtml": 2
        },
        "sentences": {
            "juans/001.xhtml": [
                "蘇悉地羯羅供養法卷第一三藏法師善無畏譯歸命諸如來，及法菩薩眾",
                "次獻塗香華、燒香及飲食、燃燈供養法；真言并手印，運心供養法；",
                "相貌相應而奉請尊。蘇悉地羯羅供養法卷第一天喜三年九月七日書了"
            ],
            "juans/002.xhtml": [
                "蘇悉地羯羅供養法卷第二三藏法師善無畏集譯次除遣從魔法者，有毘",
                "輪，從凡入佛地。」蘇悉地羯羅供養法卷第二請火天oṃebhye"
            ]
        }
    },
    "T0895b": {
        "total": 1,
        "pages": {
            "juans/001.xhtml": 1
        },
        "sentences": {
            "juans/001.xhtml": [
                "為有罪耶？為真言有加減耶？為供養法不具足耶？願為眾生分別解說"
            ]
        }
    },
    "T0897": {
        "total": 2,
        "pages": {
            "juans/001.xhtml": 1,
            "juans/002.xhtml": 1
        },
        "sentences": {
            "juans/001.xhtml": [
                "及善解畫曼荼羅法，又明念誦及供養法，具如是等一切法事。學內外"
            ],
            "juans/002.xhtml": [
                "經奉請供養品第八「次說奉請及供養法：作曼荼羅畢及觀視已，出外"
            ]
        }
    },
    "T0898": {
        "total": 1,
        "pages": {
            "juans/001.xhtml": 1
        },
        "sentences": {
            "juans/001.xhtml": [
                "障難相辟除方法，亦須善學以火供養法，及獻非人食法，迎喚發遣諸"
            ]
        }
    },
    "T0900": {
        "total": 1,
        "pages": {
            "juans/001.xhtml": 1
        },
        "sentences": {
            "juans/001.xhtml": [
                "法三種，當部明王網火院，六者供養法三種，閼伽花座普供養，初二"
            ]
        }
    },
    "T0901": {
        "total": 16,
        "pages": {
            "juans/002.xhtml": 2,
            "juans/003.xhtml": 1,
            "juans/005.xhtml": 2,
            "juans/006.xhtml": 1,
            "juans/007.xhtml": 1,
            "juans/008.xhtml": 4,
            "juans/009.xhtml": 1,
            "juans/010.xhtml": 1,
            "juans/012.xhtml": 3
        },
        "sentences": {
            "juans/002.xhtml": [
                "養，從十二月八日起首至十五日供養法事竟，當取中心水罐灌受法人",
                "金剛、天等(云云)。還作香花供養法事，悲泣雨淚，取龍腦香可一"
            ],
            "juans/003.xhtml": [
                "嚼楊柳枝更漱口訖，入佛堂中作供養法，未到食時悉皆發遣，一日三"
            ],
            "juans/005.xhtml": [
                "者，作此印呪悉皆不成。毘俱知供養法印(印是第十，用大心呪，梵",
                "前大心呪，種種有驗。毘俱知華供養法印呪(印第十三，呪第十五)"
            ],
            "juans/006.xhtml": [
                "唐云隨誦成驗)——雖不受持壇供養法，隨誦成驗。縛毘那夜迦呪第"
            ],
            "juans/007.xhtml": [
                "訶(四)』「若呪師日日作一切供養法時，發遣已竟，以右手大指、"
            ],
            "juans/008.xhtml": [
                "握右手腕下。「是一法印，若於供養法會壇中，以寶盆宬水而著雜華",
                "作此印，請喚來去。軍茶利香花供養法印第十(用大心呪)「以二無",
                "一切金剛皆悉歡喜。軍茶利飲食供養法印第十一(用大心呪)「准前",
                "不安隱。「治病亦爾，而作種種供養法事，總事已竟，又作是印，更"
            ],
            "juans/009.xhtml": [
                "身、頭上，誦呪即差。烏樞沙摩供養法印呪第五「準前身印，惟改以"
            ],
            "juans/010.xhtml": [
                "復取蓮華一百八箇以供養之。其供養法，手取一一蓮華一一呪之，用"
            ],
            "juans/012.xhtml": [
                "，取諸證成。我今欲作護身結界供養法事，在此院內東西南北、四維",
                "香華、五盤飲食、然十六燈而作供養法事已竟。次阿闍梨出道場，迎",
                "音十一面菩薩大心呪，悉通一切供養法用。「次阿闍梨作一切佛、般"
            ]
        }
    },
    "T0913": {
        "total": 2,
        "pages": {
            "juans/001.xhtml": 2
        },
        "sentences": {
            "juans/001.xhtml": [
                "諸天部五日、藥叉部四日也)。供養法皆用日初出時辨壇食、甘美香",
                "，如事不獲已三七日亦得，此火供養法以資念誦令速成就。其阿毘遮"
            ]
        }
    },
    "T0914": {
        "total": 1,
        "pages": {
            "juans/001.xhtml": 1
        },
        "sentences": {
            "juans/001.xhtml": [
                "即諸魔不能穢惡。兼用虛空庫心供養法，最不可思議。布置供養具訖"
            ]
        }
    },
    "T0921": {
        "total": 2,
        "pages": {
            "juans/001.xhtml": 2
        },
        "sentences": {
            "juans/001.xhtml": [
                "No.921阿閦如來念誦供養法一卷開府儀同三司特進試鴻臚卿肅",
                "合引)訶(引)」阿閦如來念誦供養法一卷"
            ]
        }
    },
    "T0925": {
        "total": 1,
        "pages": {
            "juans/002.xhtml": 1
        },
        "sentences": {
            "juans/002.xhtml": [
                "業報不虛，乃至命難亦不造業。供養法者大德阿難！若有病人及餘災"
            ]
        }
    },
    "T0926": {
        "total": 2,
        "pages": {
            "juans/001.xhtml": 2
        },
        "sentences": {
            "juans/001.xhtml": [
                "璃光王七佛本願功德經念誦儀軌供養法大元三藏沙門沙囉巴奉詔譯我",
                "璃光王七佛本願功德經念誦儀軌供養法"
            ]
        }
    },
    "T0927": {
        "total": 2,
        "pages": {
            "juans/001.xhtml": 2
        },
        "sentences": {
            "juans/001.xhtml": [
                "報由自證見，乃至命難亦不造惡供養法則。』復告大德阿難：『若有",
                "倫，國富民安增壽故；演說壇儀供養法，救脫菩薩我敬禮。廣嚴城會"
            ]
        }
    },
    "T0951": {
        "total": 3,
        "pages": {
            "juans/002.xhtml": 2,
            "juans/005.xhtml": 1
        },
        "sentences": {
            "juans/002.xhtml": [
                "、遏伽花等持獻供養，及諸佛頂供養法中亦不供養；應以惹底花、[",
                "養世間天神。如斯供獻名三種族供養法則。「愚癡嬰人無所曉解，種"
            ],
            "juans/005.xhtml": [
                "呪仙神，亦通塗香、散花、燒香供養法用。摧碎頂輪王印之七「准根"
            ]
        }
    },
    "T0952": {
        "total": 3,
        "pages": {
            "juans/002.xhtml": 3
        },
        "sentences": {
            "juans/002.xhtml": [
                "、遏迦花等時獻供養，及諸佛頂供養法中亦勿供養，應以惹底花、頭",
                "獻世間天神，如斯供獻名三種族供養法則。「愚癡嬰人無所曉解，種",
                "佛實說，亦不虛施，但精專至修供養法、扇底迦法、布瑟置迦法、阿"
            ]
        }
    },
    "T0953": {
        "total": 2,
        "pages": {
            "juans/003.xhtml": 2
        },
        "sentences": {
            "juans/003.xhtml": [
                "故？天子！法身者是如來身，若供養法即為供養如來。」爾時，世尊",
                "種種金銀真珠瓔珞，從自頸脫為供養法故捨施供養。爾時，世尊告一"
            ]
        }
    },
    "T0981": {
        "total": 1,
        "pages": {
            "juans/001.xhtml": 1
        },
        "sentences": {
            "juans/001.xhtml": [
                "八遍若千八十為限。遍數畢，作供養法，然後本尊諸尊奉送於本宮。"
            ]
        }
    },
    "T0985": {
        "total": 1,
        "pages": {
            "juans/003.xhtml": 1
        },
        "sentences": {
            "juans/003.xhtml": [
                "以牛糞塗地。此是孔雀王呪尋常供養法式，凡有所求皆可依法作此壇"
            ]
        }
    },
    "T1030": {
        "total": 1,
        "pages": {
            "juans/001.xhtml": 1
        },
        "sentences": {
            "juans/001.xhtml": [
                "，是與諸部同。結界已，即結諸供養法等，復以香花飲食供養。供養食"
            ]
        }
    },
    "T1050": {
        "total": 2,
        "pages": {
            "juans/004.xhtml": 2
        },
        "sentences": {
            "juans/004.xhtml": [
                "薩摩訶薩以四大洲滿中七寶奉獻供養法師。於是法師告言：「今所供養，",
                "彼除蓋障復以價直百千真珠瓔珞供養法師，時彼法師言：「善男子！"
            ]
        }
    },
    "T1072A": {
        "total": 1,
        "pages": {
            "juans/002.xhtml": 1
        },
        "sentences": {
            "juans/002.xhtml": [
                "波帝吒悉陀波泮底，雖不受持壇供養法隨誦成驗。「次加持念珠真言"
            ]
        }
    },
    "T1074": {
        "total": 1,
        "pages": {
            "juans/001.xhtml": 1
        },
        "sentences": {
            "juans/001.xhtml": [
                "(唐云隨誦成驗)，雖不受持壇供養法隨誦成驗。若欲發遣何耶揭唎"
            ]
        }
    },
    "T1075": {
        "total": 1,
        "pages": {
            "juans/001.xhtml": 1
        },
        "sentences": {
            "juans/001.xhtml": [
                "亂，方可入此祕密法門。凡念誦供養法，於所在處皆須清淨澡浴著新"
            ]
        }
    },
    "T1092": {
        "total": 1,
        "pages": {
            "juans/024.xhtml": 1
        },
        "sentences": {
            "juans/024.xhtml": [
                "羅尼真言曼拏羅印像三昧耶，所供養法各別皆有無量無邊三昧耶門，"
            ]
        }
    },
    "T1153": {
        "total": 1,
        "pages": {
            "juans/001.xhtml": 1
        },
        "sentences": {
            "juans/001.xhtml": [
                "。』彼貧匱人於長者家營事，復供養法。於過後時，其長者子與一金"
            ]
        }
    },
    "T1157": {
        "total": 1,
        "pages": {
            "juans/001.xhtml": 1
        },
        "sentences": {
            "juans/001.xhtml": [
                "。初以三壇，一用供養佛、一用供養法、一用供養僧，第四壇供養阿"
            ]
        }
    },
    "T1171": {
        "total": 1,
        "pages": {
            "juans/001.xhtml": 1
        },
        "sentences": {
            "juans/001.xhtml": [
                "金剛頂經瑜伽文殊師利菩薩儀軌供養法一品歸命童真妙吉祥，我依瑜"
            ]
        }
    },
    "T1177A": {
        "total": 1,
        "pages": {
            "juans/010.xhtml": 1
        },
        "sentences": {
            "juans/010.xhtml": [
                "福無福？若供養僧其福百倍，若供養法其福千倍，若供養佛其福萬倍"
            ]
        }
    },
    "T1184": {
        "total": 1,
        "pages": {
            "juans/001.xhtml": 1
        },
        "sentences": {
            "juans/001.xhtml": [
                "尼，若有男子女人不能辦作承事供養法者，復緣在家迫迮作種種生業"
            ]
        }
    },
    "T1185A": {
        "total": 1,
        "pages": {
            "juans/001.xhtml": 1
        },
        "sentences": {
            "juans/001.xhtml": [
                "羅尼，若男子女人不能辦作承事供養法者，在家迫迮作種種家業，但"
            ]
        }
    },
    "T1204": {
        "total": 1,
        "pages": {
            "juans/001.xhtml": 1
        },
        "sentences": {
            "juans/001.xhtml": [
                "其頸肩。畫像法，說已竟。次說供養法。行者欲陳供養者，先須發菩"
            ]
        }
    },
    "T1212": {
        "total": 1,
        "pages": {
            "juans/001.xhtml": 1
        },
        "sentences": {
            "juans/001.xhtml": [
                "，常誦吉祥呪及結界呪，作承事供養法，常誦軍荼利心呪一千八遍。"
            ]
        }
    },
    "T1231": {
        "total": 2,
        "pages": {
            "juans/001.xhtml": 2
        },
        "sentences": {
            "juans/001.xhtml": [
                "231大輪金剛修行悉地成就及供養法我依《金剛頂經》略述大輪持",
                "經行。大輪金剛修行悉地成就及供養法時寬延二歲次己巳七月穀旦"
            ]
        }
    },
    "T1249": {
        "total": 1,
        "pages": {
            "juans/001.xhtml": 1
        },
        "sentences": {
            "juans/001.xhtml": [
                "香華菓子，外院著乳粥餅等。香供養法真言：摩拏阿羅他鉢哩布囉迦"
            ]
        }
    },
    "T1251": {
        "total": 4,
        "pages": {
            "juans/001.xhtml": 2,
            "juans/002.xhtml": 2
        },
        "sentences": {
            "juans/001.xhtml": [
                "/寸]字，即八大曼荼羅相，並供養法相也。彼[阿-可+(俱/寸",
                "[阿-可+(俱/寸)]曼荼羅供養法竟。」「次又可說[仁-二+"
            ],
            "juans/002.xhtml": [
                "傳即法悉滅盡。若有人護人護摩供養法印至心奉供，若起他念即法不",
                "切災難消滅乞，次解界若請召等供養法，次只此一品法作，次可作若"
            ]
        }
    },
    "T1254": {
        "total": 1,
        "pages": {
            "juans/001.xhtml": 1
        },
        "sentences": {
            "juans/001.xhtml": [
                "復取蓮華一百八箇以供養之。其供養法，手取一一蓮華呪之，用以供養。"
            ]
        }
    },
    "T1270": {
        "total": 3,
        "pages": {
            "juans/001.xhtml": 3
        },
        "sentences": {
            "juans/001.xhtml": [
                "身大自在天毘那夜迦王歸依念誦供養法三藏沙門善無畏譯大聖自在天",
                "那訶(誦七遍令沐浴)第二念誦供養法。佛母心印。二手內縛當頞，",
                "合*牛](三遍)次寂心澄念作供養法。金剛合掌，誦呪：唵惡娑婆"
            ]
        }
    },
    "T1302": {
        "total": 1,
        "pages": {
            "juans/001.xhtml": 1
        },
        "sentences": {
            "juans/001.xhtml": [
                "神，瞋怒云何而殄滅？祕密言辭供養法，今當次第而宣說。」爾時釋"
            ]
        }
    },
    "T1320": {
        "total": 1,
        "pages": {
            "juans/001.xhtml": 1
        },
        "sentences": {
            "juans/001.xhtml": [
                "白)。運心供養(《蘇悉地羯羅供養法》下卷中說：運心供養者，想"
            ]
        }
    },
    "T1340": {
        "total": 2,
        "pages": {
            "juans/009.xhtml": 1,
            "juans/013.xhtml": 1
        },
        "sentences": {
            "juans/009.xhtml": [
                "得無量福。如來世尊復如是說：供養法師即為供養諸佛如來應供正遍"
            ],
            "juans/013.xhtml": [
                "卷第十三隋天竺三藏闍那崛多譯供養法師品第三十佛告阿難：「爾時"
            ]
        }
    },
    "T1374": {
        "total": 1,
        "pages": {
            "juans/001.xhtml": 1
        },
        "sentences": {
            "juans/001.xhtml": [
                "！若復有人聞此經典，不生信心供養法師者，我於是人無有方便能為"
            ]
        }
    },
    "_stat_": {
        "found_epubs": 55,
        "found_juans": 77,
        "total": 127
    }
}