{
    "T0896": {
        "total": 1,
        "pages": {
            "juans/001.xhtml": 1
        },
        "sentences": {
            "juans/001.xhtml": [
                "加行若立，善法增長亦復如是。「又，持誦人要在攝心，不得歌舞戲"
            ]
        }
    },
    "T0940": {
        "total": 2,
        "pages": {
            "juans/001.xhtml": 2
        },
        "sentences": {
            "juans/001.xhtml": [
                "加行，於現生中得見慈氏菩薩。我今樂聞，願佛為說。」爾時佛告大",
                "加行於現生中求見慈氏菩薩，或復樂求聖劍、聖輪、如意寶、教法、"
            ]
        }
    },
    "T0945": {
        "total": 2,
        "pages": {
            "juans/008.xhtml": 1,
            "juans/010.xhtml": 1
        },
        "sentences": {
            "juans/008.xhtml": [
                "加行。即以佛覺用為己心，若出未出，猶如鑽火欲然其木，名為煖地"
            ],
            "juans/010.xhtml": [
                "加行心、菩薩所行金剛十地、等覺圓明，入於如來妙莊嚴海；圓滿菩"
            ]
        }
    },
    "T0950": {
        "total": 3,
        "pages": {
            "juans/001.xhtml": 1,
            "juans/002.xhtml": 1,
            "juans/004.xhtml": 1
        },
        "sentences": {
            "juans/001.xhtml": [
                "加行修習、曼茶羅印契安布異成就事業、一字轉輪王佛頂入於大三摩"
            ],
            "juans/002.xhtml": [
                "加行故，本尊速現前。以何成真言，慇懃成自身？以施、戒、忍辱、"
            ],
            "juans/004.xhtml": [
                "加行修習求成就，尚於夢中無愛染。先知真言三昧耶、曼茶羅法等差"
            ]
        }
    },
    "T0951": {
        "total": 2,
        "pages": {
            "juans/001.xhtml": 1,
            "juans/002.xhtml": 1
        },
        "sentences": {
            "juans/001.xhtml": [
                "加行印壇入三摩地、上中下法、成就法處、坐法、臥法、誦法、持法"
            ],
            "juans/002.xhtml": [
                "加行法行則得成就。是故，密跡主！呪何所成？要從身心勤懇布施、"
            ]
        }
    },
    "T0952": {
        "total": 2,
        "pages": {
            "juans/001.xhtml": 1,
            "juans/002.xhtml": 1
        },
        "sentences": {
            "juans/001.xhtml": [
                "加行壇印種種事法、一字轉輪王法、入大三摩地壇處成就法、念誦之"
            ],
            "juans/002.xhtml": [
                "加行法行則得成就。」復謂：「密迹！呪何所成就？從身勤懇布施、"
            ]
        }
    },
    "T0953": {
        "total": 6,
        "pages": {
            "juans/001.xhtml": 3,
            "juans/002.xhtml": 2,
            "juans/003.xhtml": 1
        },
        "sentences": {
            "juans/001.xhtml": [
                "加行，往菩提場摧魔，現證菩提轉法輪，般涅槃住法隱法。與四萬比",
                "加行。』如是灌頂者，即為阿闍梨，入一切菩提道，如是於菩薩行行",
                "加行謗佛教者，於像前，或人髑髏前，以人髑髏末作彼人形，面向北"
            ],
            "juans/002.xhtml": [
                "加行，以善業趣於善。得善助伴不為罪業，作善加行趣於善已，承事"
            ],
            "juans/003.xhtml": [
                "加行者，作利益安樂，令獲得不退轉菩薩地故，令入一切如來教，安"
            ]
        }
    },
    "T1003": {
        "total": 1,
        "pages": {
            "juans/001.xhtml": 1
        },
        "sentences": {
            "juans/001.xhtml": [
                "加行位，護持修行、辟除諸障。成菩提時，摧伏天魔及摩醯首羅一切"
            ]
        }
    },
    "T1005A": {
        "total": 1,
        "pages": {
            "juans/001.xhtml": 1
        },
        "sentences": {
            "juans/001.xhtml": [
                "加行相應故，得成正覺。金剛手！此陀羅尼，有大威力、有大殊勝，"
            ]
        }
    },
    "T1009": {
        "total": 4,
        "pages": {
            "juans/001.xhtml": 4
        },
        "sentences": {
            "juans/001.xhtml": [
                "加行得不難。若世界如殑伽沙，悉皆捨施滿七寶，書持從所生福德，",
                "加行菩薩摩訶薩，有八大藥叉住雪山中，皆來增加修行者身威力，晝",
                "加行修習陀羅尼，加行菩薩住實期信，知恩報恩愛樂佛法，住深法忍"
            ]
        }
    },
    "T1018": {
        "total": 1,
        "pages": {
            "juans/001.xhtml": 1
        },
        "sentences": {
            "juans/001.xhtml": [
                "加行，乃至能知一切世間所有諸法皆悉不離自心而起，此是菩薩第二"
            ]
        }
    },
    "T1019": {
        "total": 2,
        "pages": {
            "juans/001.xhtml": 2
        },
        "sentences": {
            "juans/001.xhtml": [
                "加行般若波羅蜜門，娜悟一切法調伏寂靜真如平等無分別故。「ba",
                "加行藏蓋差別道場般磋(上)若波羅蜜門，悟一切法欲樂覆性不可得"
            ]
        }
    },
    "T1033": {
        "total": 1,
        "pages": {
            "juans/001.xhtml": 1
        },
        "sentences": {
            "juans/001.xhtml": [
                "加行倍復精進。若失成就，夢旃陀羅、毘舍遮鬼惡形狀者，或見人身"
            ]
        }
    },
    "T1050": {
        "total": 4,
        "pages": {
            "juans/004.xhtml": 4
        },
        "sentences": {
            "juans/004.xhtml": [
                "加行觀智一切相應，汝於未來當得是微妙心法。彼觀自在菩薩摩訶薩",
                "加行遍歷無數百千萬俱胝那庾多世界，到彼無量壽如來所，在前合掌",
                "加行志求解脫，如是之人應與；不應與外道異見。』是時無量壽如來",
                "加行志求冥應，與是六字大明王矣。」時彼法師觀見虛空中蓮華手蓮"
            ]
        }
    },
    "T1092": {
        "total": 1,
        "pages": {
            "juans/018.xhtml": 1
        },
        "sentences": {
            "juans/018.xhtml": [
                "加行數數現前。四應圓滿隨諸有情善根應熟，故入諸有自現化生，謂"
            ]
        }
    },
    "T1096": {
        "total": 1,
        "pages": {
            "juans/001.xhtml": 1
        },
        "sentences": {
            "juans/001.xhtml": [
                "加行苦行乃得成佛，佛智甚難得。何況其餘凡夫之人，云何由此少分"
            ]
        }
    },
    "T1108A": {
        "total": 1,
        "pages": {
            "juans/001.xhtml": 1
        },
        "sentences": {
            "juans/001.xhtml": [
                "加行極摧壞，展左踡右作足踏，頂髻熾盛極明耀。敬禮都哩大緊母，"
            ]
        }
    },
    "T1108B": {
        "total": 1,
        "pages": {
            "juans/001.xhtml": 1
        },
        "sentences": {
            "juans/001.xhtml": [
                "加行極摧壞，展左踡右作足踏，頂髻熾盛極明耀。紅色敬禮都哩大緊"
            ]
        }
    },
    "T1120A": {
        "total": 1,
        "pages": {
            "juans/001.xhtml": 1
        },
        "sentences": {
            "juans/001.xhtml": [
                "加行精勤，又演念誦門，四威儀修習，如前願拔濟，無餘界有情，亦"
            ]
        }
    },
    "T1130": {
        "total": 1,
        "pages": {
            "juans/001.xhtml": 1
        },
        "sentences": {
            "juans/001.xhtml": [
                "加行，所作呪法皆得成。金剛杵形畫相似，及以蓮華形相好，應於露"
            ]
        }
    },
    "T1177A": {
        "total": 1,
        "pages": {
            "juans/007.xhtml": 1
        },
        "sentences": {
            "juans/007.xhtml": [
                "加行位中修持十迴向，學耎、頂、忍、世第一法，名為次第修證成就"
            ]
        }
    },
    "T1320": {
        "total": 2,
        "pages": {
            "juans/001.xhtml": 2
        },
        "sentences": {
            "juans/001.xhtml": [
                "加行畢，首座秉爐胡跪白佛)南無歸依十方盡虛空界一切諸佛南無歸",
                "加行位菩薩知之。自身想觀自在菩薩，心月輪上想一白色hrīḥ字"
            ]
        }
    },
    "T1361": {
        "total": 17,
        "pages": {
            "juans/001.xhtml": 17
        },
        "sentences": {
            "juans/001.xhtml": [
                "加行清淨者當知，即於波羅蜜多相應善根而起加行。淨心果者，無上",
                "加行清淨者，即是解脫。所謂轉依，無上之智及於解脫，而非加行清",
                "加行更互相待，為究竟故。謂由所有一切資糧無所得心修習迴向即得",
                "加行清淨者當知，即於波羅蜜多相應善根而起加行」，如經「我諸所",
                "加行清淨者即是解脫」者，為顯果也。其相云何？論曰「所謂轉依」",
                "加行清淨果耶」者，謂當說彼是其果也。云何是彼淨心之果？論曰「",
                "加行更互相待為究竟故」，謂獨淨心或唯加行，於彼無有無上正等菩",
                "加行。言「無所得心修習」者，無染善心而修習故，謂不染著我法故",
                "加行彼一切果，是故決定應如是知。若不如是，所修淨心而空其果，",
                "加行。「般若大悲平等所攝」者，謂智及悲平等之性，即名智悲平等",
                "加行故。論曰「如是所修六門之者，得六功德」者，謂如所說六種加",
                "加行也。論曰「四於諸菩薩而不見有微細忘誤善觀斷除」者，第四果"
            ]
        }
    },
    "T1419": {
        "total": 1,
        "pages": {
            "juans/001.xhtml": 1
        },
        "sentences": {
            "juans/001.xhtml": [
                "加行位、三通達位亦名見道位、四修習位、五究竟位也。地，即十地"
            ]
        }
    },
    "_stat_": {
        "found_epubs": 24,
        "found_juans": 31,
        "total": 59
    }
}