{
    "T0848": {
        "total": 2,
        "pages": {
            "juans/003.xhtml": 1,
            "juans/004.xhtml": 1
        },
        "sentences": {
            "juans/003.xhtml": [
                "遍生圓光，如劫災猛焰，寶冠舉手印，能怖一切惡，降伏諸魔軍。」"
            ],
            "juans/004.xhtml": [
                "如前，作五股金剛戟形，是寶印手印。彼真言曰：「『南麼三曼多勃"
            ]
        }
    },
    "T0850": {
        "total": 1,
        "pages": {
            "juans/003.xhtml": 1
        },
        "sentences": {
            "juans/003.xhtml": [
                "此成幖幟，餘相廣如經。寶冠舉手印，住於字門者，事業速成就。」"
            ]
        }
    },
    "T0852a": {
        "total": 1,
        "pages": {
            "juans/002.xhtml": 1
        },
        "sentences": {
            "juans/002.xhtml": [
                "此字門者，事業疾成就。寶冠舉手印(五股)，身行輪布之，眉間、"
            ]
        }
    },
    "T0852b": {
        "total": 1,
        "pages": {
            "juans/002.xhtml": 1
        },
        "sentences": {
            "juans/002.xhtml": [
                "此字門者，事業疾成就，寶冠舉手印，身行輪布之，眉間、咽、心、"
            ]
        }
    },
    "T0853": {
        "total": 2,
        "pages": {
            "juans/001.xhtml": 1,
            "juans/002.xhtml": 1
        },
        "sentences": {
            "juans/001.xhtml": [
                "亦還三禮讚。真言曰(持地印。手印有四名，其右智手，云毘鉢舍那"
            ],
            "juans/002.xhtml": [
                "此字門者，事業疾成就。寶冠舉手印(五股)，身行輪布之，眉間咽"
            ]
        }
    },
    "T0855": {
        "total": 3,
        "pages": {
            "juans/001.xhtml": 3
        },
        "sentences": {
            "juans/001.xhtml": [
                "瑜)音、彌勒，形色莊嚴，面貌手印幖幟等皆如儀軌。一一種子一一",
                "次第而分敷(中初)。次寶冠舉手印(外五置頂額，誦加命五種阿)",
                "次諸奉教者(普通印)。次金剛手印。次忙莽鷄。次金剛針。次金剛"
            ]
        }
    },
    "T0866": {
        "total": 2,
        "pages": {
            "juans/002.xhtml": 1,
            "juans/004.xhtml": 1
        },
        "sentences": {
            "juans/002.xhtml": [
                "同用此法散之。「次結金剛縛拍手印而令歡喜，即說密語：「唵跋折"
            ],
            "juans/004.xhtml": [
                "是畫像壇，即隨有空處置之；若手印壇，即於壇上置之)，各想其部"
            ]
        }
    },
    "T0868": {
        "total": 6,
        "pages": {
            "juans/002.xhtml": 2,
            "juans/003.xhtml": 4
        },
        "sentences": {
            "juans/002.xhtml": [
                "腰上，此名金剛不退轉印。結此手印，作如是想：『我今未得成佛已",
                "池皆悉青色。』作此觀已，次結手印，以其兩手作金剛拳，舒二頭指"
            ],
            "juans/003.xhtml": [
                "我是金剛鎖。』作此想已，便結手印。先以左右母指頭指更互相鉤，",
                "眼，擊於腦後。時彼弟子結金剛手印，以十指頭更互相叉，皆內掌中",
                ")「復次，阿闍梨教於弟子令結手印，改前金剛手印，竪左右中指繫"
            ]
        }
    },
    "T0882": {
        "total": 2,
        "pages": {
            "juans/022.xhtml": 1,
            "juans/030.xhtml": 1
        },
        "sentences": {
            "juans/022.xhtml": [
                "如本儀，諸寶標幟各執持，及彼手印如次第。「此等大明曰：「唵("
            ],
            "juans/030.xhtml": [
                "「蓮華拳印左手結，復當蓋覆其手印，隨處成結法相應，速得蓮華法"
            ]
        }
    },
    "T0893a": {
        "total": 7,
        "pages": {
            "juans/001.xhtml": 2,
            "juans/002.xhtml": 3,
            "juans/003.xhtml": 2
        },
        "sentences": {
            "juans/001.xhtml": [
                "得真言後退本心亦不可與；乃至手印及以真言并功能法及普行法並不",
                "見。「入曼荼羅了，應當授與結手印法及真言，并以法則亦應正說，"
            ],
            "juans/002.xhtml": [
                "食無可獻者，但誦本色真言及作手印以此獻之。表云：『無可求得，",
                "尊真言而加持水，遍請護摩及作手印等。「佛部真言曰：「『唵怛他",
                "本座，然後誦計利吉里真言并作手印復淨其火，一切護摩皆應如是。"
            ],
            "juans/003.xhtml": [
                "就之物用兩種法為作護：一、謂手印；二、白芥子。令成就物速有驗",
                "獻閼伽，如法分與誦本真言及作手印，以心觀念本尊及誦明王妃真言"
            ]
        }
    },
    "T0893b": {
        "total": 8,
        "pages": {
            "juans/001.xhtml": 2,
            "juans/002.xhtml": 4,
            "juans/003.xhtml": 2
        },
        "sentences": {
            "juans/001.xhtml": [
                "梨所受得真言亦不可與彼，及至手印及以真言并功能法及普行法並不",
                "「既入曼荼羅畢已，應當授與結手印法及真言等明藏法則，復應廣為"
            ],
            "juans/002.xhtml": [
                "食無可獻者，但誦本色真言及此手印以此獻之。表云：『供物無可求",
                "尊真言，而真言水遍請護摩及輪手印。「佛部請火天真言：「『[盍",
                "為除穢故應誦計利吉里真言并作手印；為衛護故軍荼利真言，水灑作",
                "於本座。復誦計利吉里真言并作手印復淨其火，一切護摩皆應如是。"
            ],
            "juans/003.xhtml": [
                "之物用兩種法以為作護：一、謂手印；二、白芥子。令成就物速有驗",
                "獻閼伽如法分與，誦本真言及作手印，以心觀念本尊及誦明王明妃真"
            ]
        }
    },
    "T0893c": {
        "total": 10,
        "pages": {
            "juans/001.xhtml": 4,
            "juans/002.xhtml": 2,
            "juans/003.xhtml": 4
        },
        "sentences": {
            "juans/001.xhtml": [
                "闍梨所受得真言亦不可與；乃至手印及以真言，并功能法及普行法并",
                "居之方，觀念本尊持誦真言及作手印，取水三掬想浴本尊并奉閼伽，",
                "莎嚩(去二合)訶(四)』「其手印相：二手仰掌側相著，以二頭指",
                "心。「入曼荼羅了，應當授與結手印法及持真言次第法則，應正廣為"
            ],
            "juans/002.xhtml": [
                "之物用兩種法以為作護：一、謂手印；二、白芥子。令成就物速有驗",
                "閼伽，如法分與。誦本真言及作手印，以心觀念本尊及誦明王明妃真"
            ],
            "juans/003.xhtml": [
                "食無可獻者，但誦本色真言及此手印以此獻之，表云：『供物無可求",
                "尊真言，而真言水遍請護摩及倫手印。「佛部請火天真言：「『唵(",
                "為除穢故應誦計利吉里真言并作手印；為衛護故軍荼利真言水灑作淨",
                "於本座；後誦計利吉里真言并作手印復淨其火。一切護摩皆應如是。"
            ]
        }
    },
    "T0894a": {
        "total": 167,
        "pages": {
            "juans/001.xhtml": 89,
            "juans/002.xhtml": 55,
            "juans/003.xhtml": 23
        },
        "sentences": {
            "juans/001.xhtml": [
                "復明其事法；對受得真言，及作手印法；於外出入處，分土洗淨法；",
                "香及飲食、燃燈供養法；真言并手印，運心供養法；讚歎懺悔等，護",
                "乃至令作諸餘灌頂。對受真言及手印者，謂受法人澡浴清淨，著新潔",
                "，恭敬對阿闍梨，親受真言及作手印。時阿闍梨先誦三遍，轉授與彼",
                "之[合*牛]若(而也反)」其手印相，以右手作拳，直竪大母指，",
                ")吽訶(上)(三遍誦之)」其手印相，以右手直舒五指，指頭相博",
                "合)闇(引)(三遍誦之)」其手印相，以右手作拳，直竪大指，頭",
                "，教如是說。次說三摩耶真言及手印。初佛部真言曰：「唵怛他(去",
                "之)」此是佛部三摩耶真言。其手印相，仰兩手十指直向前舒並側相",
                "，微屈兩頭指上節(此是三摩耶手印)。次說蓮華部三摩耶真言及手印",
                "耶真言)」其莎、訶皆去音。其手印相，先當合掌，中間兩手六指向",
                "屈中間六指(此是蓮花部三摩耶手印)。次說金剛部三摩耶真言及手印",
                "之，此是金剛三摩耶真言)」其手印相，右押左，兩手背逆相著，以",
                "開，如三股杵(此是金剛三摩耶手印)。結縛諸難者，謂以軍荼利手印",
                "以軍荼利手印真言而縛諸難。其手印相，左手置於右手膊跟上，以大",
                "五遍誦之，此是淨土真言)」其手印相，兩手相叉，指捻手背，雙竪",
                "二大母指並竪，博頭指側(以此手印蓋所取土，誦真言五遍，然後取",
                "(七遍誦之，此辟除真言)」其手印相，以左手大指屈入掌中，以中",
                "此是辟除印)。又，辟除真言及手印。真言曰：「唵嚩日囉(二合)",
                "牛]泮吒(此是辟除真言)」其手印相，以右手指左手掌，如是三遍",
                "指左手掌，如是三遍(此是辟除手印)。又，辟除真言及手印。真言",
                "]泮吒(輕此是辟除真言)」其手印相，以兩手各作彈指聲三遍(此",
                "除印)。護身法者，以此真言及手印用結十方界及以護身。真言曰：",
                "焰莎訶(此護身結界真言)」其手印相，以右手大指捻小指甲上，餘",
                "是結界護身等印)。次以真言、手印用印自身及以水土澡豆等物，便",
                "七遍誦之，此是瀉垢真言)」其手印相，以右手大指捻小指甲上，餘",
                "是瀉垢印)。次以軍荼利真言及手印用作清淨。真言曰：「唵闇沒㗚",
                "七遍誦之，此是清淨真言)」其手印相，以右手作拳取水念誦七遍，",
                "淨(此是清淨印)。次以真言及手印用作光澤。真言曰：「唵枳里枳",
                "七遍誦之，此是光澤真言)」其手印相，以左手大指捻小指甲上，餘",
                "以右手作此印承左手肘下，以右手印印諸觸物及以己身即成光澤(此",
                "澤(此是光澤印)。次以真言及手印用攪其水。真言曰：「唵[合*",
                "數，惟多誦此是攪水真言)」其手印相，兩手向外相叉，以二大指並",
                "著(此是攪水印)。次以真言及手印取土塗身。真言曰：「唵部囉若",
                "七遍誦之，此是塗土真言)」其手印相，取土和水，兩手相揩，以右",
                "土塗身印)。次以軍荼利真言、手印持誦水真言，曰：「唵闇沒㗚(",
                "遍誦之，此是持誦水真言)」其手印相，先平舒右手，以大指押其中",
                "(此是持誦水印)。次以真言及手印遣除身中毘那夜迦難，真言曰：",
                "是遣除身中毘那夜迦真言)」其手印相，以兩手大指屈入掌中作拳，",
                "迦印)。次則應以軍荼利真言及手印護身五處，真言曰：「唵嚩日囉",
                "五遍誦之，此是護身真言)」其手印相，以二小指相叉入掌中，無名",
                "身(此是護身印)。次以真言及手印持誦一一分土。真言曰：「唵度",
                "遍誦之，此是持誦土真言)」其手印相，以二手頭指、小指頭相著，",
                "印)。次誦軍荼利根本真言攪以手印水，隨意澡浴。真言曰：「囊(",
                "言)」其灌頂真言，以此真言及手印而自灌頂。真言曰：「唵賀臛(",
                "泮吒(三遍誦此灌頂真言)」其手印相，以二小指相叉入掌，二無名",
                "頂(此是灌頂印)。次以真言及手印而自結髮。真言曰：「唵蘇悉地",
                "此是結髮真言，通三部用)」其手印相，右手作拳，直舒大母指，以",
                "居之方觀念本尊，持誦真言及作手印，以印掬水而獻之。想浴本尊及",
                "金剛部奉三掬水真言)」通三部手印相，平仰兩手，側相著，以二頭",
                "奉浴本尊(此是通三部奉三掬水手印)。往於神室者，謂入向道場之",
                "六洗手及足，用前所說護淨真言手印飲水拭唇如前。重更飲水灑淨已",
                "淨真言)」又，說佛部飲水灑淨手印，仰舒右手，屈無名指向內，勿",
                "水印)。又，說蓮華部飲水灑淨手印，仰舒右手，無名指向內，勿令",
                "是金剛部灑淨水印)。次以真言手印灑淨門外所授之衣。真言曰：「",
                "莎訶(此是灑淨換衣真言)」其手印相，以右手作拳，取水持誦，用",
                "持誦，用灑淨衣(此是灑淨換衣手印)。次以真言持誦其衣而著。真",
                "[合*牛](此是著衣真言，無手印)」入室便禮者，如教所說，行",
                "之，此是佛部三麼耶真言)」其手印相，仰兩手，十指直向前舒並側",
                "屈二頭指上節(此是佛部三麼耶手印)。次說蓮華部三麼耶真言及手印",
                "，此是蓮華部三麼耶真言)」其手印，先相當合掌，中間兩手六指向",
                "屈中間六指(此是蓮花部三麼耶手印)。次說金剛部三麼耶真言及手印",
                "，此是金剛部三麼耶真言)」其手印相，右押左，兩手背逆相著，以",
                "，如三股杵(此是金剛部三麼耶手印)此三印名為大印。諸佛菩薩猶",
                "求之法必得順願。次應以真言及手印遣除身中毘那夜迦難。真言曰：",
                "遣除身中毘那夜迦難真言)」其手印相，以兩手大指屈入掌中作拳，",
                "略去之(此是遣除毘那夜迦難等手印)。次應以真言及手印辟除。真",
                "七遍誦之，此是辟除真言)」其手印相，以左手大指屈入掌中，以中",
                "此是辟除印)。又，辟除真言及手印。真言曰：「唵嚩日囉(二合)",
                "三遍誦之，此是辟除真言)」其手印相，以右手拍左手掌，如是三遍",
                "拍左手掌，如是三遍(此是辟除手印)。又，辟除真言及手印。真言",
                "牛]泮吒(此是辟除真言)」其手印相，以兩手彈指三遍(此是辟除",
                "相，以兩手彈指三遍(此是辟除手印)。云何名為辟除？謂於神室、",
                "名辟除，即得清淨。次說真言及手印而作瀉垢。真言曰：「唵枳里枳",
                "七遍誦之，此是瀉垢真言)」其手印相，以右手大指捻小指甲上，餘",
                "惡，名曰瀉垢(此枳里忿怒瀉垢手印)。次作清淨，佛部心真言，而",
                "真言)」次作光澤，持真言及作手印以印諸物便成光澤。初佛部光澤",
                "之，此是金剛部光澤真言)」其手印相，以左手大指捻小指甲上，餘",
                "右手亦作此印，承左手肘下，以手印印觸諸物即成光澤，通三部用(",
                "澤，通三部用(此是通三部光澤手印)。◎蘇悉地羯羅供養法卷上丹"
            ],
            "juans/002.xhtml": [
                "三藏善無畏譯◎次作護身法明王手印，誦此真言，印頂……等五處，",
                "」五遍誦之，此是護身真言。其手印相，二小指叉入掌，二無名雙押",
                "大指直竪，輔著中指(此是護身手印)。次作大護身，誦此真言及作",
                ")。次作大護身，誦此真言及作手印，亦五處，成大護身。真言曰：",
                "遍誦之，此是大護身真言)」其手印相即前護身印同。次應被甲，誦",
                "身印同。次應被甲，誦真言及作手印，從頂摩觸，下至於足，即成被",
                "七遍誦之，此是被甲真言)」其手印相，散舒。次以真言及手印，而",
                "此是結髮真言，通三部用)」其手印相，右手作拳，直舒大母指，印",
                "之，此是金剛部結髮真言)」其手印相與前印同。置其寶座者，本尊",
                "伽水持誦置於左邊。辦事真言及手印，前所說辟除等真言、手印是也",
                "、手印是也。次說部母等真言及手印。初說佛部母真言曰：「囊(上",
                "指，押二中指上節背(此是佛根手印相)。次說蓮華部母手印相，合",
                "相著(此是蓮花母半拏羅嚩祇寧手印)。次說金剛部母忙莽計手印相",
                "並直竪相著(此是金剛母忙莾計手印)。又說合掌屈二頭指及二無名",
                "並竪相著(亦即是)。次說部心手印相。初佛部心手印相，八指相叉",
                "隨作法處先想坐已，次以真言、手印成就車輅，送本尊所。車輅真言",
                "(此是通三部送車輅真言)」其手印相，二手中指以下六指相叉，右",
                "指互相著掌(此是通三部送車輅手印)。送車輅已，即應誦以此明，",
                "即應誦以此明，中安來句，及作手印，或但獨請本尊、或并眷屬召請",
                "此明次應置迎句，准上可知。其手印，依前車輅印，惟改右大指與左",
                "爾囊邇迦(二十五遍誦之)」其手印相，依前部心印，惟改以二大指",
                "路力迦(輕)(五遍誦之)」其手印相，依前部心，惟改以右大指向",
                "二合)迦(引輕)(五遍)」其手印相，依前部心印，惟改左大指向",
                "，請尊至，即用枳里枳里真言及手印而遣除之。真言曰：「唵枳里枳",
                "誦之，此是枳里枳里真言)」其手印相，以左手大指捻小指甲，竪三",
                "誦之，此是視三麼耶真言)」其手印相，以右手大指捻小指甲，竪三",
                "及日暮時，於此三時以其真言、手印奉蓮華座。初佛部真言曰：「唵",
                "訶(此是金剛部奉座真言)」其手印相，合掌二手，頭指、中指、無",
                "离+土]真言，三遍誦之)」其手印相，以左手中指、無名指向外，",
                "土]印)。次以金剛鉤欄真言及手印用結上方界。真言曰：「唵微娑",
                "遍誦，此是金剛鉤欄真言)」其手印相，依前[檎-离+土]印，惟",
                "金剛鉤欄印)。以金剛爐真言、手印作金剛爐。真言曰：「唵薩羅薩",
                "]泮吒(此是金剛爐真言)」其手印相，依前[檎-离+土]印，惟",
                "內相也)。次以金剛羂索真言、手印結東方界。真言曰：「唵嚩日囉",
                "誦之，此是金剛羂索真言)」其手印相，以左手頭指屈著大指根，以",
                "結東方界)。次以金剛幡真言及手印法結西方界。真言曰：「唵鉢鐙",
                "遍誦之，此是金剛幡真言)」其手印相，以左手作掌，直竪大指，舒",
                "印)。次金剛迦(引)里真言、手印結北方界。真言曰：「唵嚩日囉",
                "誦之，此是金剛迦里真言)」其手印相，以二手大指、二小指頭各相",
                "剛迦里印)。次以金剛峯真言及手印結南方界。真言曰：「唵嚩日囉",
                "遍誦之，此是金剛峯真言)」其手印相，以左手作拳，直竪大指，右",
                "」次以阿三忙銀(引)儞真言及手印普作火院。真言曰：「唵阿三瞢",
                "之，此是阿三瞢祇寧真言)」其手印相，以右手指背置左手指內令無",
                "是阿三瞢祇寧印)。次以真言及手印重結大界。真言曰：「唵商昇(",
                "遍誦之，此是結大界真言)」其手印相，以二手小指、無名指相叉入",
                "誦千遍以為成就。次說執持數珠手印之相，以右手大指捻無名指頭，",
                "穿一活兒子等珠，以部母真言、手印持誦香花而用供養，及香水灑，",
                "，及香水灑，還以此部母真言、手印請來加持釧上。復以部母真言、",
                "請來加持釧上。復以部母真言、手印次第供養，乃至持誦千遍，以捺"
            ],
            "juans/003.xhtml": [
                "塗香以此真言及本真言持誦後作手印而奉獻之。奉塗香真言曰：「伊",
                "獻塗香真言，通三部用之)」其手印相，以右手舒五指，竪掌向外，",
                "，以此真言及本真言持誦，復作手印而奉獻之。奉花真言曰：「伊(",
                "是奉花真言，通三部用之)」其手印相如車輅印，惟改二頭指相叉(",
                "香以此真言及本真言持誦，復作手印而奉獻之。奉燒香真言曰：「阿",
                "奉燒香真言，通三部用之)」其手印相，以二手小指、無名指、中指",
                "食以此真言及本真言持誦，復作手印而奉獻之。奉食真言曰：「粵灑",
                "，此是奉食，通三部用之)」其手印相，仰兩手二掌向前側相著，二",
                "燈以此真言及本真言持誦，及作手印而奉獻之。然燈真言曰：「囉訖",
                "是奉燈真言，通三部用之)」其手印相，以右手作拳，舒中指，大頭",
                "，此是下部奉燈真言)」真言并手印運心供養者，若當不辦塗香乃至",
                "養，但誦如上奉塗香等真言及作手印亦成圓滿供養。次，運心供養者",
                "此法，運心供養，誦此真言及作手印，如上所想供養皆悉成就。真言",
                "，此是成就運心供養真言)」其手印相，兩手相叉合掌，以右押左置",
                "左置於頂上(此是成就運心供養手印)。凡作供養應具此法，至誠信",
                "至誠信心，及奉閼伽皆以真言、手印持誦成就及以運心合掌置頂，方",
                "直，勿使動搖，而作念誦。以其手印而執數珠置當心前而作念誦，先",
                "左轉其印，前所能護並悉解，其手印相准奉請印，惟改二大指向外送",
                "遍誦之，此是請火神真言)」其手印相，以右手直竪五指，舒掌向外",
                "在掌中，大指來去(此是請火神手印)。請以，右灑香水三遍及與三",
                "。」次以枳里枳里忿怒王真言及手印重作瀉垢火等。真言曰。「唵枳",
                "合)(此是瀉垢火等真言)」其手印相，左手竪五指，掌向外，右手竪",
                "乃至解界准方可發遣。其遣火神手印相如前請火神印，惟改頭指與大"
            ]
        }
    },
    "T0894b": {
        "total": 161,
        "pages": {
            "juans/001.xhtml": 117,
            "juans/002.xhtml": 44
        },
        "sentences": {
            "juans/001.xhtml": [
                "復明其事法；對受得真言，及作手印法；於外出入處，分土洗淨法；",
                "香及飲食、燃燈供養法；真言并手印，運心供養法；讚歎懺悔等，護",
                "作息災等諸餘灌頂。對受真言及手印者，謂受法人澡浴清淨，著新潔",
                "，恭敬對阿闍梨，親受真言及作手印。時阿闍梨先誦三遍，轉授與彼",
                "拕曩(上聲)[合*牛]若」其手印相，以右手作拳，直竪大指，當",
                "為限。其三聚土以受觸真言及用手印印土，持誦經一七遍然後用也，",
                "[合*牛]訶(誦三反之)」其手印相，以右手仰掌直舒五指，指[",
                "踞而默然，兩手置於雙膝之間，手印掬水，勿有泡沫，無聲飲之。三",
                "說如是。往澡浴時，先以此明及手印護諸供養具，然後可往。明曰：",
                "尸却囉嚩日哩闇(三遍誦)」其手印相，以右手作拳，直竪大指，頭",
                "，教如是說。次說三摩耶真言及手印。初佛部真言曰：「oṃtat",
                "引)也莎hā訶(誦三遍)」其手印相，仰兩手十指直向前舒並側相",
                "耶印。次說蓮華部三摩耶真言及手印。真言曰：「oṃpadmād",
                "(引)也莎訶(誦三遍之)」其手印相，先當合掌，中間兩六指向外",
                "耶印。次說金剛部三摩耶真言及手印。真言曰：「oṃvajrod",
                "(引)也莎訶(誦三遍之)」其手印相，右押左，兩手背逆相著，以",
                "印。次結縛諸難者，謂以軍荼利手印、真言而縛諸難。其手印相，左",
                "，先取淨土分作三聚，以真言、手印各持誦之。真言曰(三玄妙印在",
                "五遍誦之，此是淨土真言)」其手印相，兩手相叉，指捻手背，雙竪",
                "二大母指並竪，博頭指側。以此手印觸所取土，誦真言五遍然後取之",
                "誦七遍之，此是辟除真言)」其手印相，以左手大指屈入掌中，以中",
                "，此是辟除印。又，辟除真言及手印。真言曰：「oṃvajrat",
                "*牛]泮吒(是辟除真言)」其手印相，以右手拍左手掌，如是三遍",
                "手拍左手掌，如是三遍，是辟除手印。又，辟除真言及手印。真言曰",
                "合*牛]泮吒(辟除真言)」其手印相，以右手彈三遍，是辟除手印",
                "印。次，護身法者，以此真言及手印用結十方界及以護身。真言曰：",
                "焰莎訶(是護身結界真言)」其手印相，以右手大指捻小指甲上，餘",
                "及八方界并用護身。次以真言、手印用印自身，以水、土、澡豆等物",
                "吒(七遍誦之，去垢真言)」其手印相，以右手大指捻小指甲上，餘",
                "，即成去垢及與清淨，此是去垢手印。次以軍荼利真言及手印用作清",
                "唵闇沒㗚帝[合*牛]泮吒」其手印相，以右手作拳取水，念誦七遍",
                "拳四指勿令著掌)。次以真言及手印用作光澤。真言曰：「oṃjv",
                "(誦三遍之，是光澤真言)」其手印相，以左手大指捻小指甲上，餘",
                "以右手作此印承左手肘下，以左手印印觸諸物及以己身即成光澤，是",
                "成光澤，是光澤印。次以真言及手印用攪其水。真言曰：「oṃhū",
                "合)拏hā訶(攪水真言)」其手印相，兩手向外相叉，屈著手背，",
                "甲相著，是攪水印。次以真言及手印取土塗身。真言曰：「oṃbh",
                "(誦七遍之，是塗身真言)」其手印相，取土和水，兩手大指各押小",
                "塗土洗身印。次以軍荼利真言、手印持誦水真言，曰：「oṃamṛ",
                "合*牛]泮吒(誦七遍之)」其手印相，先平舒右手，先屈中指、無",
                "澡浴印(誦水印)。次以真言及手印遣除身中毘那夜迦難。真言曰：",
                "]泮吒(除身中毘那夜迦)」其手印相，以兩手大指屈入掌中，各各",
                "夜迦印。次則應以軍荼利真言及手印護身五處。真言曰：「oṃva",
                "多也莎hā訶(護身真言)」其手印相，以二小指相叉入掌中，二無",
                "成護身，是護身印。次以真言及手印持誦一一分土。真言曰：「oṃ",
                "ā里寧莎訶(三遍誦真言)」其手印相，以二手頭指及小指令頭相跓",
                "從頸至頂。畢已，還誦真言及作手印。隨意澡洗還作此印，亦誦真言",
                "澡洗還作此印，亦誦真言，並其手印遍轉於身，當心身後解印，是名",
                "遍)」其自灌頂者，以此真言及手印而自灌頂。真言曰：「oṃha",
                "吒(誦三遍，是灌頂真言)」其手印相，二小指相叉入掌中，二無名",
                "灌頂，此是灌頂印。次以真言及手印而自結髮。真言曰：「oṃsa",
                "訶(三誦三遍，通三部用)」其手印相，右手作拳，直舒大指，以頭",
                "指押大指頭上令使縛圓曲，作此手印持誦真言三遍已，置於頂上即成",
                "居之方觀念本尊，持誦真言及作手印，以印掬水而獻三掬，想浴本尊",
                ")莎嚩訶(誦三遍奉掬水)」其手印相，平仰兩手，側相著，以二頭",
                "應須解之。以阿三忙祇寧真言，手印左轉即成解結。真言曰：「oṃ",
                ")吽泮吒(此是解界真言)」其手印相，以右手背置左掌內，令無縫",
                "立，洗手及足，用前所說真言、手印重更飲水並灑淨之。佛部飲水灑",
                "尼[合*牛]」說佛部飲水灑淨手印，仰舒右手，屈無名指中節向內",
                "，勿著掌。次說蓮華部飲水灑淨手印，仰舒右手，屈無名指中節及小",
                "，勿令著掌。說金剛部飲水灑淨手印，仰舒右手，屈無名指向內，勿",
                "，散開頭指、小指。次以真言、手印灑淨門外所換之衣。真言曰：「",
                "莽囉莎嚩訶(是灑衣真言)」其手印相，以右手作拳，取水持誦，用",
                "二合)嚩也莎訶(誦五遍)」其手印相，仰兩手，十指直向前舒並側",
                "微屈二頭指上節，是佛部三麼耶手印。次說蓮華部三摩耶真言及手印",
                "挪婆嚩也莎嚩訶(誦五遍)」其手印相，先當合掌，中間兩手六指向",
                "耶印。次說金剛部三麼耶真言及手印。真言曰：「oṃvajrad",
                "]挪婆嚩也莎嚩訶(五遍)」其手印相，右押左，兩手背逆相著，以",
                "開，如三股杵，是金剛部三麼耶手印。次應以真言及手印遣除身中毘",
                "帝賀囊賀囊[合*牛]泮吒」其手印相，以兩手大指屈入掌中，以中",
                "毘那夜迦等難印。次應以真言及手印辟除。真言曰：「namova",
                "娑瑜瑳囉也泮吒(誦七遍)」其手印相，以左手大指屈入掌中，以中",
                "前，是辟除印。又，辟除真言及手印。真言曰：「oṃvajrat",
                "[合*牛]泮吒(誦三遍)」其手印相，以右手拍左手掌，如是三遍",
                "遍，是辟除印。又，辟除真言及手印。真言曰：「oṃkiliki",
                ")[合*牛]phaṭ泮吒」其手印相，以右手彈指三遍，是辟除印",
                "辟除也，即得清淨。次以真言及手印而作去垢。真言曰：「oṃki",
                "[合*牛]泮吒(誦七遍)」其手印相，以右手大指捻小指甲上，餘",
                "勒迦」次作光澤，持誦真言及作手印，以印諸物便成光澤。初佛部光",
                "羅也滿度哩莎訶(誦三遍)」其手印相，以左手大指捻小指甲上，餘",
                "手亦作此印，承左手肘下，以左手印印觸諸物即成光澤，此通三部用",
                "此通三部用。次作護身，結明王手印，誦此真言，印頂……等五處，",
                "去)鉢多也莎訶(誦三遍)」其手印相，二小指叉入掌，二無名指雙",
                "印。次作大護身，誦此真言及作手印，亦印五處成大護身。真言曰：",
                "[合*牛]泮吒(誦五遍)」其手印相即前護身印同。次應被甲誦真",
                "護身印同。次應被甲誦真言及作手印，從頂摩觸下至於足，即成被甲",
                "āhā里寧莎訶(誦七遍)」其手印相，散舒內手十指，此是被甲印",
                "十指，此是被甲印。次以真言及手印而用結髮。真言曰：「oṃsu",
                "羯里莎嚩訶(通三部用之)」其手印相，右手作拳，直舒大指，印於",
                "吒儜簸多也沙訶(誦七遍)」其手印相與前結髮印同。次置其寶座者",
                "ā唵迦莽羅莎訶(誦三遍)」其手印相，合掌兩手，叉其十指，以右",
                "器持誦，置於左邊。辦事真言及手印，前所說辟除等真言、手印是也",
                "手印是也。次說三部母等真言及手印者。初說佛部母真言曰：「na",
                "屈頭指，押中指上節背，是佛根手印。次說蓮華部母半拏羅嚩私寧手印",
                "仍腕相著。次說金剛部母忙莽計手印相，合掌屈二頭指及二無名指入",
                "餘六指並直竪相著。次說佛部心手印相。初佛部心手印相，八指相叉",
                "隨作法處先想座已。次以真言、手印成就車輅，送本尊所。車輅真言",
                "*牛](此真言通三部送)」其手印相，二手中指以下六指相叉入掌",
                "不令腕相著，六指互相著掌，此手印通三部奉送車輅。奉送車輅已，",
                "，即應誦以此明，中安來句及作手印，或但獨請本尊、或并眷屬召請",
                "囉灑(此中安來句)也莎訶」其手印，依前車輅印，唯改右大指與左",
                "改右大指與左手中指頭相著，此手印通三部奉請印。或以部心真言，",
                "。或以部心真言，中置來句及作手印而請。若以部心真言奉請本尊，",
                "唵爾囊邇迦(誦二十五遍)」其手印相，依前部心印，唯以二大指向",
                "唵阿路力迦(誦二十五遍)」其手印相，依前部心印，唯以右大指向",
                "(二合)迦(誦二十五遍)」其手印相，依前部心印，改左大指，向",
                "清淨，及成警覺本尊。先作奉請手印，即誦此句一遍，次即應誦奉請"
            ],
            "juans/002.xhtml": [
                "請尊至已，即用枳里枳里真言及手印而除遣之。真言曰：「oṃki",
                "[合*牛]泮吒(誦七遍)」其手印相，以右手大指捻小指甲，直竪",
                "託之，將此枳里枳里金剛真言及手印而用除遣之。次視三昧耶者，作",
                ")]三摩焰莎訶(誦七遍)」其手印相，以右手大指捻小指甲，竪三",
                "三遍，通用持誦閼伽真言)」其手印相，以護身印，改其母指置於頭",
                "及日暮時，於此三時以其真言、手印奉蓮華座供養本尊。初佛部奉座",
                "唵嚩日囉味囉(引)也莎訶」其手印相，二手合掌，頭指、中指、無",
                "[合*牛]泮吒(誦三遍)」其手印相，以左手中指、無名指向外，",
                "+土]印。次以金剛鉤欄真言及手印用結上方界。真言曰：「oṃv",
                "[合*牛]泮吒(誦三遍)」其手印相，依前[檎-离+土]印，唯",
                "是金剛鉤欄牆印。金剛牆真言、手印。金剛牆真言曰：「oṃsar",
                "phaṭ囉[合*牛]泮吒」其手印相，依前[檎-离+土]印，唯",
                "金剛爐印。次以金剛羂索真言、手印結東方界。真言曰：「oṃva",
                "ṃ囉[合*牛](誦三遍)」其手印相，以左手頭指屈著大指根下，",
                "金剛羂索印。次以金剛幡真言及手印結西方界。真言曰：「oṃpa",
                "唵鉢鐙祗寧囉吒(誦三遍)」其手印相，以左手作拳，直竪大指，舒",
                "亦是此印。次以金剛迦利真言、手印結北方界。真言曰：「oṃva",
                "囉迦里囉吒莽吒(誦三遍)」其手印相，以二手大指、二小指令頭相",
                "尸佉囉嚕吒莽吒(誦三遍)」其手印相，以左手作拳，直竪大指，右",
                "七遍)」次以阿三忙祇寧真言及手印普作火院。真言曰：「oṃas",
                "[合*牛]泮吒(誦三遍)」其手印相，以右手指背置左手指內，令",
                "，是阿三忙祇寧印。次以真言及手印重結大界。真言曰：「oṃśa",
                "，是三重界內結大界真言)」其手印相，以二手小指、無名指相叉入",
                "誦千遍以為成就。次說執持數珠手印之相，以右手大指捻無名指頭，",
                "指，微屈頭指著中指上節側，是手印通三部用，是佛部數珠印。次說",
                "穿一活兒子等珠，以部母真言、手印持誦香華而用供養及香水灑，還",
                "養及香水灑，還以此部母真言、手印請來加持釧上，復以部母真言、",
                "真言及本部真言持誦加護，復作手印而奉獻之。奉塗香真言曰：「i",
                "帝莎訶(七遍，通三部用)」其手印相，以右手舒五指，竪掌向外，",
                "向外，大指在內把之，是奉塗香手印，通三部用。又，佛部奉塗香真",
                "華以此真言及本真言持誦，復作手印而奉獻之。奉華真言曰：「im",
                "誦七遍，奉華真言通三部)」其手印相如前車輅印，唯改二大指博二",
                "香以此真言及本真言持誦，復作手印而奉獻之。奉燒香真言曰：「a",
                "莎訶(誦七遍，通三部用)」其手印相，以二手小指、無名指、中指",
                "食以此真言及本真言持誦，復作手印而奉獻之。奉食真言曰：「oṣ",
                "莎訶(誦七遍，通三部用)」其手印相，仰兩手掌向上，側相著，二",
                "燈以此真言及本真言持誦，復作手印而奉獻之。奉然燈真言曰：「r",
                "ā莎訶(誦七遍，三部用)」其手印相，以右手作拳舒中指，大指頭",
                "]泮吒(七遍)」次，真言并及手印運心供養者，若當不辦塗香乃至",
                "養，但誦如上奉塗香等真言及作手印，亦成圓滿供養。次，運心供養",
                "行此法，運心供養誦持真言及作手印，如上所想皆悉成就。真言曰：",
                "門伽伽囊劍莎訶(誦七遍)」其手印相，兩手相叉合掌，以右押左置",
                "置於頂上，此是成就運心供養具手印。凡作供養應具此法，至誠信心",
                "法，至誠信心及奉閼伽皆以真言手印持誦成就，及以運心合掌置頂，"
            ]
        }
    },
    "T0895a": {
        "total": 5,
        "pages": {
            "juans/001.xhtml": 2,
            "juans/002.xhtml": 1,
            "juans/003.xhtml": 2
        },
        "sentences": {
            "juans/001.xhtml": [
                "養，以香泥揩手，勿以觸手而結手印。念誦之時應坐茅草，若不辦諸",
                "錯亂，繫心於本尊，或思真言并手印等。由如入定心勿散亂，調伏諸"
            ],
            "juans/002.xhtml": [
                "心，觀真言字句，或觀本尊或觀手印。譬如觀行之人，置心眉間令不"
            ],
            "juans/003.xhtml": [
                "明妃。「復說種種妙曼荼羅及諸手印，我利益貧窮眾生，及摧諸鬼類",
                "說三十萬真言。「各各俱說真言手印及曼荼羅，依法受持。若為此教"
            ]
        }
    },
    "T0895b": {
        "total": 4,
        "pages": {
            "juans/001.xhtml": 1,
            "juans/002.xhtml": 3
        },
        "sentences": {
            "juans/001.xhtml": [
                "錯亂，繫心於尊。或於真言及以手印，調伏諸根，端坐尊前，心不散"
            ],
            "juans/002.xhtml": [
                "迴心，攀真言字，或觀本尊或觀手印。譬如觀行之人，置心眉間令不",
                "中明妃。復說種種妙漫荼羅及諸手印，我為利益貧窮眾生，及摧諸鬼",
                "及妃等，各各俱說數千萬真言及手印漫荼羅，依法受持，若違此教非"
            ]
        }
    },
    "T0896": {
        "total": 1,
        "pages": {
            "juans/004.xhtml": 1
        },
        "sentences": {
            "juans/004.xhtml": [
                "七俱胝真言，并種種曼拏羅及諸手印，為利益一切貧窮眾生及摧伏一"
            ]
        }
    },
    "T0897": {
        "total": 11,
        "pages": {
            "juans/001.xhtml": 1,
            "juans/002.xhtml": 1,
            "juans/003.xhtml": 9
        },
        "sentences": {
            "juans/001.xhtml": [
                "僧，惠施一切貧窮困苦。明解大手印等一切諸印及善解畫曼荼羅法，"
            ],
            "juans/002.xhtml": [
                "誦百遍，然後次第應作諸尊一一手印持誦三遍。如是作已，悉皆歡喜"
            ],
            "juans/003.xhtml": [
                "印、解放難印……如是等印，於手印品皆悉廣說。如前所說淨治及護",
                "如前所說淨治及護身法，其皆用手印相應而作。「若欲碎伏難伏者，",
                "滅諸障難者，當用遜婆明王真言手印。作此法已，其諸難等皆被火燒",
                "，誦彼真言三遍。次作曼荼羅主手印置於頂上，誦彼真言三遍，引將",
                "種真言持誦其瓶，於其頂上而作手印，并誦根本真言，還誦此真言與",
                "視其曼荼羅，解說諸尊，教視本手印相，復教明王真言，次教今坐一",
                "餘灌頂者，應教所得真言本法及手印法。「若有愚人不入曼荼羅，持",
                "以此法與弟子者，先教明王真言手印及大手印諸曼荼羅，然後方與此"
            ]
        }
    },
    "T0898": {
        "total": 1,
        "pages": {
            "juans/001.xhtml": 1
        },
        "sentences": {
            "juans/001.xhtml": [
                "法，及獻非人食法，迎喚發遣諸手印呪法等。又復須知居住之地，或"
            ]
        }
    },
    "T0899": {
        "total": 1,
        "pages": {
            "juans/001.xhtml": 1
        },
        "sentences": {
            "juans/001.xhtml": [
                "想四壁及地皆是七寶合成，即結手印，諸本呪神降起道場，授弟子供"
            ]
        }
    },
    "T0901": {
        "total": 21,
        "pages": {
            "juans/001.xhtml": 7,
            "juans/002.xhtml": 3,
            "juans/003.xhtml": 2,
            "juans/004.xhtml": 1,
            "juans/005.xhtml": 2,
            "juans/007.xhtml": 2,
            "juans/010.xhtml": 2,
            "juans/012.xhtml": 2
        },
        "sentences": {
            "juans/001.xhtml": [
                "七遍，即名地結界。四角四方以手印空中轉，呪七遍，即是結八方界",
                "轉，呪七遍，即是結八方界。以手印頂上一尺高轉呪七遍，即名上結",
                "轉呪七遍，即名上結界法。次用手印總結界竟，手執香鑪，燒種種香",
                "頭指漸漸屈入掌；呪滿七遍，反手印，即和南頂禮，向內散去奉請印",
                "闍(五)莎婆訶』「誦七遍已，手印隨日轉。轉三匝已，次應勅云：",
                "明印頭頂上著，誦呪七遍，右轉手印呪三七遍，手印向右髆前著，翹"
            ],
            "juans/002.xhtml": [
                "十一(唐云栴檀德佛)「准馬頭手印，惟改屈二大指入掌，以二中指",
                "誦呪，有身印等種種印法，若作手印、誦諸呪法，易得成驗。若未曾",
                "未曾入灌頂壇者，不得輒作一切手印。若人誦此陀羅尼者，即同入壇"
            ],
            "juans/003.xhtml": [
                "、寶物供等；若有金剛杵，不用手印，直當用杵而作加持。無嚩日囉",
                "作加持。無嚩日囉(二合)即用手印，以左手作總印，大指捻小指甲"
            ],
            "juans/004.xhtml": [
                "問三答。「如是答竟，次阿闍梨手印香鑪、水等，呪已，手執香鑪胡"
            ],
            "juans/005.xhtml": [
                "，大好益善。又千轉印呪第二「手印與前一切觀世音心印同，惟足不",
                "，屈膝並坐，以右手拓地，用左手印綜三指，當胸前著，腰屈向前。"
            ],
            "juans/007.xhtml": [
                "指押中指節上，頭指直竪。以左手印，中立著跋折囉，屈肘覆掌，當",
                "掌中，竪二大指已，起立，舉右手印，努向頭上，以向下打一切鬼勢"
            ],
            "juans/010.xhtml": [
                "欲受法證効驗者，必須作壇及其手印；若不如是，徒喪其功。「且作",
                "後口云結界，一聲即成——莫作手印及呪灰等——隨行者願皆得成就"
            ],
            "juans/012.xhtml": [
                "問三答)徒眾答已，然後阿闍梨手印香鑪及淨水等，用馬頭印印其淨",
                "呪打諸弟子心，人各一遍。次作手印，一一印之。次以香水一一灑身"
            ]
        }
    },
    "T0917": {
        "total": 1,
        "pages": {
            "juans/001.xhtml": 1
        },
        "sentences": {
            "juans/001.xhtml": [
                "，獨一靜處半跏而坐已，須先作手印護持，以檀慧並合竪，其戒忍方"
            ]
        }
    },
    "T0924C": {
        "total": 2,
        "pages": {
            "juans/001.xhtml": 2
        },
        "sentences": {
            "juans/001.xhtml": [
                "向道場者，先澡浴清淨，以真言手印，灑淨所換之衣。次以真言加持",
                "此法。運心供養，誦持真言及作手印，如上所想皆悉成就。真言曰："
            ]
        }
    },
    "T0938": {
        "total": 1,
        "pages": {
            "juans/001.xhtml": 1
        },
        "sentences": {
            "juans/001.xhtml": [
                "說法，漸漸誘彼令入佛道。次說手印。如來鉢印：先以右手當心仰掌"
            ]
        }
    },
    "T0939": {
        "total": 1,
        "pages": {
            "juans/001.xhtml": 1
        },
        "sentences": {
            "juans/001.xhtml": [
                "(二合)紇陵(二合)惡儀相及手印相並依法則，安於輪外四隅之位"
            ]
        }
    },
    "T0946": {
        "total": 2,
        "pages": {
            "juans/004.xhtml": 2
        },
        "sentences": {
            "juans/004.xhtml": [
                "畏寶廣聚如來佛頂總攝一切諸部手印品第二十二復說壇呪成就吉祥誦",
                "千俱胝那庾多印並作以訖，名字手印。又呪雖別，並同用此印。「如"
            ]
        }
    },
    "T0947": {
        "total": 1,
        "pages": {
            "juans/001.xhtml": 1
        },
        "sentences": {
            "juans/001.xhtml": [
                "指漸漸屈入掌，呪滿十一遍，及手印和南頂禮向內散去。奉請印請作"
            ]
        }
    },
    "T0951": {
        "total": 2,
        "pages": {
            "juans/004.xhtml": 2
        },
        "sentences": {
            "juans/004.xhtml": [
                "方大壇城界。「入壇中院，又結手印，頂上一尺右轉七匝，誦呪七遍",
                "指漸漸屈入於掌；呪滿七遍，并手印和南頂禮，向內散印，是印力能"
            ]
        }
    },
    "T0955": {
        "total": 1,
        "pages": {
            "juans/001.xhtml": 1
        },
        "sentences": {
            "juans/001.xhtml": [
                "色相。一切於本部主，應與於右手印物為次第，於金剛縛中，安物類"
            ]
        }
    },
    "T0969": {
        "total": 1,
        "pages": {
            "juans/001.xhtml": 1
        },
        "sentences": {
            "juans/001.xhtml": [
                "也)，所作皆成(誦呪有身印、手印，作印誦呪法即易成。若未入壇"
            ]
        }
    },
    "T0973": {
        "total": 26,
        "pages": {
            "juans/001.xhtml": 22,
            "juans/002.xhtml": 4
        },
        "sentences": {
            "juans/001.xhtml": [
                "加印處，並誦真言而加持之。其手印相：智定相叉，齊輪合掌，以智",
                "二)怛囉(二合)吒(三)」其手印相：作前金剛掌印，便合作拳，",
                "，無諸障難。當以降三世真言及手印而加持，各能成辦諸事等。次誦",
                "牛](四)」此名降三世尊言及手印，名成辦諸事者。其印相：智定",
                "地水火三輪押之即成。其印以定手印置在心上，以智印用觸諸物，及",
                "二)底瑟吒(二合)(三)」其手印相：智、定二手，地輪鉤鎖相連",
                "是名發生之印。次請本尊等真言手印。發請真言曰：「oṃvajr",
                "二)惹惹(重急呼)(三)」其手印相：以智、定相叉，作金剛拳。",
                "惹(急重呼)(三)jaḥ」其手印相：用降三世印，以二風輪舉作",
                "跛捨(二)吽(三)hūṃ」其手印相：以金剛拳竪二地輪，二空輪",
                ")阿(短急呼)(三)aḥ」其手印相：作金剛拳竪二地輪，二空輪",
                "合)底瑟姹(二合)(五)」其手印相：智、定相拍，便成堅固。次",
                "二合)(二)諾迦咤(去)」其手印相：以其智手水輪、空輪相捻，",
                "(二合)(二)度弊(三)」其手印相：作金剛拳按其香上，持誦真",
                "二)扶瑟(二合)弊(三)」其手印相：合金剛掌，用印加持，誦真",
                "(二合)(二)地幣(三)」其手印相：作金剛拳，竪二大空置於心",
                "(二合)(二)誐度(三)」其手印相：智、定覆掌，散舒其輪，以",
                "怛跛(二合)陀夜弭(三)」其手印相：合金剛掌，發菩提心，持誦",
                "此法，運心供養，誦持真言及作手印，如上所想悉皆成就。運心真言",
                "誦真言七遍，即成普通供養。其手印相：作合金剛掌置於頂上，誦此",
                "合*牛](三)泮吒(四)」其手印相：兩手內相叉為拳，竪直二中",
                "(二合)謨乞灑(二合)謀」其手印相：智、定相叉作金剛拳，向頂"
            ],
            "juans/002.xhtml": [
                "要須先用一切佛頂輪王心真言及手印、難勝忿怒王真言手印辟除護身",
                "合*牛](三)泮吒(四)」其手印相者：以兩手勾，內叉十指合掌",
                "、辟除等，以難勝忿怒王真言及手印便成辦事，一切處用。難勝忿怒"
            ]
        }
    },
    "T0976": {
        "total": 2,
        "pages": {
            "juans/001.xhtml": 2
        },
        "sentences": {
            "juans/001.xhtml": [
                "般帝娑醯夜耶眾南謨無愛子五大手印而敬禮眾南謨摧三界城樂處寒林",
                "金剛炬白母，蓮華日月光。「諸手印眾，願擁護我願擁護我。「唵唎"
            ]
        }
    },
    "T0977": {
        "total": 3,
        "pages": {
            "juans/001.xhtml": 3
        },
        "sentences": {
            "juans/001.xhtml": [
                "屈苦行之主者等。敬禮具美嚴五手印無愛子之所歸敬處。敬禮具美能",
                "燭及白色母，蓮華眼及月光母。手印聚彼等一切力故，願令擁護於我",
                "燭及白色母，蓮華目及月光母，手印聚處稱讚禮，出有壞母白蓋母，"
            ]
        }
    },
    "T0981": {
        "total": 1,
        "pages": {
            "juans/001.xhtml": 1
        },
        "sentences": {
            "juans/001.xhtml": [
                "頭指以下四指，竪大母指，以右手印左旋三遍為辟除，右旋三遍為結"
            ]
        }
    },
    "T1000": {
        "total": 2,
        "pages": {
            "juans/001.xhtml": 2
        },
        "sentences": {
            "juans/001.xhtml": [
                "肩、心及於喉，皆誦一遍。運動手印誦真言時，專注一緣如前觀想。",
                "野娑嚩(二合)訶(引)」當運手印誦真言時，想從印及真言不思議"
            ]
        }
    },
    "T1006": {
        "total": 17,
        "pages": {
            "juans/003.xhtml": 17
        },
        "sentences": {
            "juans/003.xhtml": [
                "尊為諸眾生說陀羅尼印法。此之手印如何而作？如何安手如何安臂？",
                "尼阿吠瑟吒耶吽』「誦此呪兼作手印已，即得一切如來心印成就，獲",
                "有壇法亦速成就。若有百千萬億手印之法，此印成已，彼印即成，諸",
                "珠，解脫煩惱，積聚功德。其作手印之處即是舍利之塔，此地當有諸",
                "壓二小指甲上。結加趺坐，頂戴手印。誦此呪曰：「『唵薩婆怛他伽",
                "法輪，得仙人圍繞，一切呪法及手印、壇法恒得現前，十方諸天晝夜",
                "法忍，登佛道場，當成正覺。」手印呪品第八爾時，世尊為諸大眾說",
                "呪品第八爾時，世尊為諸大眾說手印呪法。佛言：「應於佛壇中作四",
                "尊為諸眾生說陀羅尼印法。此之手印如何而作？如何安手如何安臂？",
                "卷下唐三藏法師菩提流志奉詔譯手印品第十二爾時，世尊知眾渴仰作",
                "口*路]婆)「誦此呪已，便作手印。先以右手拇指與頭指拄，餘三",
                "(呼憾切，下同)』「誦此呪兼手印已，即得一切如來心印，成就獲",
                "有壇法亦速成就。若有百千萬億手印之法，此印成已，彼印即成，諸",
                "來瓔珞印法佛言：「我今說瓔珞手印法。應以兩手返掌於外，互以中",
                "珠，解脫煩惱、積聚功德。其作手印之處，即是舍利之塔，此地當有",
                "拄拇指中節。即結跏趺坐，頂戴手印。誦呪曰：「『唵薩婆呾他伽多",
                "法輪，得仙人圍繞。一切呪法及手印、壇法恒得現前，十方諸天晝夜"
            ]
        }
    },
    "T1007": {
        "total": 1,
        "pages": {
            "juans/001.xhtml": 1
        },
        "sentences": {
            "juans/001.xhtml": [
                "之，起四重緣，泥之訖已，即以手印念佛誦呪，迎請五神安坐爐中。"
            ]
        }
    },
    "T1035": {
        "total": 1,
        "pages": {
            "juans/001.xhtml": 1
        },
        "sentences": {
            "juans/001.xhtml": [
                "乳前勿著乳，面作笑顏頭向右(手印與觀世音心印同，唯身脚法用別"
            ]
        }
    },
    "T1057a": {
        "total": 3,
        "pages": {
            "juans/001.xhtml": 3
        },
        "sentences": {
            "juans/001.xhtml": [
                "婆，於細㲲上圖畫形質，及結壇手印經本至京進上，太武見而不珍，",
                "持寺法師智通共梵僧翻出呪經并手印等。智通法師三覆既了，即祈心",
                "羅門僧名蘇伽施，常持此法結壇手印，朝夕虔祈。琳罄折諮詢，每致"
            ]
        }
    },
    "T1058": {
        "total": 2,
        "pages": {
            "juans/001.xhtml": 2
        },
        "sentences": {
            "juans/001.xhtml": [
                "那夜迦棒印、槊印、輪印及種種手印。是諸印上皆繞遍畫火焰。又當",
                "手中各執種種器仗等印，或單結手印，皆各不同，如心經說。手腕一"
            ]
        }
    },
    "T1065": {
        "total": 4,
        "pages": {
            "juans/001.xhtml": 4
        },
        "sentences": {
            "juans/001.xhtml": [
                "上現掌。畫像已，其印相如畫像手印相。真言曰：「（七）唵縛日羅",
                "作摩身勢。畫像已，其印相如像手印。真言曰：「（九）唵嚩日羅(",
                "作拳安腰。畫像已，其印相以右手印於心上。真言曰：「（三十一）",
                "蓮華合掌。像成已，其印相如像手印。真言曰：「（三十四）唵嚩日"
            ]
        }
    },
    "T1089": {
        "total": 1,
        "pages": {
            "juans/001.xhtml": 1
        },
        "sentences": {
            "juans/001.xhtml": [
                "，受取守護，莫令散失。」又想手印，猶如寶藏，一切遍數，安在藏"
            ]
        }
    },
    "T1092": {
        "total": 33,
        "pages": {
            "juans/003.xhtml": 1,
            "juans/004.xhtml": 6,
            "juans/006.xhtml": 1,
            "juans/011.xhtml": 1,
            "juans/019.xhtml": 1,
            "juans/020.xhtml": 4,
            "juans/021.xhtml": 6,
            "juans/023.xhtml": 4,
            "juans/024.xhtml": 3,
            "juans/025.xhtml": 1,
            "juans/027.xhtml": 1,
            "juans/029.xhtml": 2,
            "juans/030.xhtml": 2
        },
        "sentences": {
            "juans/003.xhtml": [
                "摩訶薩演斯偈已，論說一切神通手印印三昧耶。「根本印：「二手合"
            ],
            "juans/004.xhtml": [
                "廣大解脫蓮華曼拏羅三昧耶種種手印、諸器仗印廣博無量，譬如大地",
                "蓮華壇，開敷蓮華臺上圖畫一切手印諸器仗印一切寶花果印者，皆繞",
                "、獄印、執鎖印、思惟印、執寶手印、執善金剛杵印、執不空蓮花印",
                "印、執五股金剛杵印、不空羂索手印、不空成就印。如是手印，皆指",
                "[合*牛](五)」「如是蓮花手印三昧耶，若常一一依三昧耶字觀"
            ],
            "juans/006.xhtml": [
                "謂現於千手千眼、輪持無量神通手印、器杖印。三界示現種種色身，"
            ],
            "juans/011.xhtml": [
                "悲心，斷諸語論，晝夜如法輪結手印，誦持最勝明王真言悉地王真言"
            ],
            "juans/019.xhtml": [
                "，一一座上開敷蓮華，臺上種種手印。次院四門置須彌山，山下大海"
            ],
            "juans/020.xhtml": [
                "黃，三兩精治銀合盛，置蓮華臺手印上，緋帛覆上法加持。時真言者",
                "，晝夜六時燒香獻，西門趺坐輪手印，誦持神通解脫心，陀羅真言心",
                "雲。四面當畫開蓮華，臺上畫諸手印相，於諸華間畫蓮鬘，四門蓮臺",
                "金剛界嚴潔。香合置於大蓮臺，手印心上緋帛蓋。置不空王觀世音，"
            ],
            "juans/021.xhtml": [
                "香，長時燒焯獻一切。大蓮華臺手印上，置於藥合便加持。作斯法者",
                "面四角開敷蓮華，其心臺上羂索手印，寶釧莊嚴。一一葉上三股金剛",
                "印、期剋印、毘日稟皤印、安慰手印、無畏手印、與願手印、合掌印",
                "又四面周匝開敷蓮華，臺上種種手印，一一印上燒火光焰。內一院界"
            ],
            "juans/023.xhtml": [
                "蓮華。一一臺上次第當畫五十八手印真言，繞字光焰。四門臺上金剛",
                "如是不空大奮怒王三昧耶五十八手印真言書畫曼拏羅者，有大威德、",
                "諸印誦是真言者，則令壇中所畫手印、所結手印皆現種種通用神變，"
            ],
            "juans/024.xhtml": [
                "而坐，俱虛空中一時顯現。一切手印、一切器仗印乃至諸印種種相狀",
                "三摩地者當證一切三摩地，不結手印者當結手印，未見一切佛法僧寶"
            ],
            "juans/025.xhtml": [
                "上月輪，於月輪上置此部中一切手印。四門如意寶瓶印，四角金剛鉤"
            ],
            "juans/027.xhtml": [
                "剛杵印、三股金剛蓮華印、一切手印，是諸印上燒火光焰。四門蘇彌"
            ],
            "juans/029.xhtml": [
                "，未授三昧耶與授三昧耶，未授手印與授手印，未得真言明與得真言"
            ],
            "juans/030.xhtml": [
                "院四面開敷蓮華，於華臺上置諸手印、諸器仗印，一一印上繞火光焰",
                "敷蓮華，於華臺上諸器仗印及諸手印繞火光焰。四角，須彌寶山。山"
            ]
        }
    },
    "T1096": {
        "total": 1,
        "pages": {
            "juans/001.xhtml": 1
        },
        "sentences": {
            "juans/001.xhtml": [
                "吉祥事已，然後令王入壇。當以手印印於其壇，印壇已送柳枝清淨，"
            ]
        }
    },
    "T1097": {
        "total": 1,
        "pages": {
            "juans/003.xhtml": 1
        },
        "sentences": {
            "juans/003.xhtml": [
                "於草上結加趺坐，以衣蒙頭作定手印，應誦不空羂索神呪王滿一千八"
            ]
        }
    },
    "T1103a": {
        "total": 1,
        "pages": {
            "juans/001.xhtml": 1
        },
        "sentences": {
            "juans/001.xhtml": [
                "手亦爾。以掌向前，如施甘露右手印法。呪曰：「跢姪他(一)阿("
            ]
        }
    },
    "T1103b": {
        "total": 1,
        "pages": {
            "juans/001.xhtml": 1
        },
        "sentences": {
            "juans/001.xhtml": [
                "手亦然，以掌向前，如施甘露右手印法。真言曰：「跢姪他阿唎跢唎"
            ]
        }
    },
    "T1110": {
        "total": 1,
        "pages": {
            "juans/001.xhtml": 1
        },
        "sentences": {
            "juans/001.xhtml": [
                "三問三答。如是答竟，次阿闍梨手印印香爐水等，誦真言已，手執香"
            ]
        }
    },
    "T1129": {
        "total": 2,
        "pages": {
            "juans/002.xhtml": 2
        },
        "sentences": {
            "juans/002.xhtml": [
                "印。復用大母指捻頭指節，以右手印安字右眼上，左手印安字左眼上"
            ]
        }
    },
    "T1141": {
        "total": 25,
        "pages": {
            "juans/001.xhtml": 25
        },
        "sentences": {
            "juans/001.xhtml": [
                "，於五部之中為普供養。其普通手印相者，以定慧二手十輪相叉齊度",
                "我]躭囉(二合)耽履三莽也其手印相，以智定二手十輪相叉合掌，",
                "障難。當用降三世尊明王真言及手印而作加持，各能成辦諸事業等。",
                "水火輪三輪押之即成。其印以定手印置在心上，以智手印用觸諸物，",
                "底*以]瑟吒(二合)(二)其手印相，以智定二手地輪鉤鎖相連，",
                ")糝忙耽(急重呼之)(一)其手印相，以智定二手相叉作金剛拳，",
                "引)俱捨耽(急重呼)(一)其手印相，以智定二手各作金剛拳，竪",
                "虎[合*牛](二合)(一)其手印相，以智定二手作金剛拳，竪二",
                "健(引)吒惡(一)(鈴也)其手印相，以智定二手作金剛拳，竪二",
                "吒[武*感](一)(鎖也)其手印相，智定二手相拍，便成堅固印",
                "二合)[牟*古]迦姹(一)其手印相，以智手水輪與大空輪相捻，",
                "(二合)度閉(一)惡(入)其手印相，以智定二手作金剛拳按其香",
                "囉(二合)補澁閉(二合)唵其手印相，以智定二手作金剛合掌，用",
                "(二合)儞閉(一)儞(入)其手印相：以智定二手作金剛拳，竪二",
                "(二合)獻度(引)(一)虐其手印相，以智定二手覆掌散舒八輪，",
                "簸(二合)曩夜(引)mi弭其手印相，以智定二手作合掌金剛，以",
                "此法，運心供養，誦持真言及作手印，如上所想皆悉成就。運心普通",
                "武*我](二合引)hā賀其一手印相，以智定二手作金剛合掌，置",
                "遍，即成就諸供養具。以真言及手印護身五處，又於手印上想一寶蓮",
                "己身五支，便成悲氏真體。法界手印曰，交叉二地水輪於掌中，以二",
                "*我](二合引)賀(四)其心手印相，以智定二手虛心合掌，以二",
                "供養香花遏囉伽(二合)等真言手印，一一如法次第廣作，發弘誓願",
                "以真無言，如言如相是真言也。手印相者，謂誓教法。即如國王勅級"
            ]
        }
    },
    "T1145": {
        "total": 11,
        "pages": {
            "juans/001.xhtml": 11
        },
        "sentences": {
            "juans/001.xhtml": [
                "出外。復以淨水重洗手已，即作手印掌承淨水，誦陀羅尼三遍便即飲",
                "水，誦陀羅尼三遍便即飲之。其手印相，先仰舒右手五指，屈其頭指",
                "去像上所覆之物。次即須作護身手印。其手印相，先舉右手，然後以",
                "并壇及近壇之地。復如前作護身手印，置塗香上，誦陀羅尼一遍。餘",
                "，華香等物即便清淨。復作護身手印，右轉三匝兼指上下，但運其印",
                "希有心，作真身解。又誦三遍，手印如前，作是念言：『今者菩薩來",
                "華、眾寶之具悉皆嚴好。』復作手印，誦陀羅尼一遍，如前想念，諸",
                "第二運心供養，法亦成就。即以手印掐珠，誦陀羅尼，明記遍數。誦",
                "時量如本已，方始出觀。又作前手印，誦陀羅尼三遍已，舉大母指發",
                "壇中，復於葉上安置酥器，還作手印誦陀羅尼三遍護持此酥。又以樹"
            ]
        }
    },
    "T1185A": {
        "total": 1,
        "pages": {
            "juans/001.xhtml": 1
        },
        "sentences": {
            "juans/001.xhtml": [
                "並當頂禮。念誦了，便結大精進手印。其印合兩手，八指反用叉皆在"
            ]
        }
    },
    "T1190": {
        "total": 4,
        "pages": {
            "juans/001.xhtml": 4
        },
        "sentences": {
            "juans/001.xhtml": [
                "性，顯作世間大種性，殊勝廣大手印種，大種大髻應觀察。言詞之主",
                "主。尊者即是法施主，宣說四種手印義，有情奉施殊勝主，決定所入",
                "聲聞緣覺之大密，一切密呪及其手印。真實增長諸不可說念及正念，",
                "神威勢無能攝伏，能成一切密呪手印記句中圍無餘。密呪明呪王并頻"
            ]
        }
    },
    "T1201": {
        "total": 1,
        "pages": {
            "juans/002.xhtml": 1
        },
        "sentences": {
            "juans/002.xhtml": [
                "堅固不散。後誦根本印明曰。其手印準前根本三昧耶是，以二手中指"
            ]
        }
    },
    "T1212": {
        "total": 3,
        "pages": {
            "juans/001.xhtml": 3
        },
        "sentences": {
            "juans/001.xhtml": [
                "看事法品第十六帶呪法品第十七手印法品第十八漫荼羅受法壇品第十",
                "即得擁護，滅一切惡。」軍荼利手印法品第十八「復次說印法。於金",
                "剛印。極作可畏相，皺眉各自作手印。遶壇四面畫金剛花鬘印。壇東"
            ]
        }
    },
    "T1222a": {
        "total": 1,
        "pages": {
            "juans/001.xhtml": 1
        },
        "sentences": {
            "juans/001.xhtml": [
                "，取密里得迦以左脚踏頭上，以手印打之，真言句中并吽字，其蜜里"
            ]
        }
    },
    "T1222b": {
        "total": 1,
        "pages": {
            "juans/001.xhtml": 1
        },
        "sentences": {
            "juans/001.xhtml": [
                "取密里得迦，以左脚踏頭上，以手印打之，真言中并吽字。其密哩得"
            ]
        }
    },
    "T1238": {
        "total": 1,
        "pages": {
            "juans/001.xhtml": 1
        },
        "sentences": {
            "juans/001.xhtml": [
                "人。若虎狼暴亂百姓人民者，以手印指之，口云：『百獸諦聽，奉上"
            ]
        }
    },
    "T1239": {
        "total": 1,
        "pages": {
            "juans/002.xhtml": 1
        },
        "sentences": {
            "juans/002.xhtml": [
                "法，若虎狼暴亂百姓人民者，以手印指之，口云：『百獸諦聽，奉上"
            ]
        }
    },
    "T1246": {
        "total": 3,
        "pages": {
            "juans/001.xhtml": 3
        },
        "sentences": {
            "juans/001.xhtml": [
                "青帝，吐氣依方吐，并請眷屬。手印品第四藥叉立身印第一以右脚直",
                "者呪師耳邊皆悉分明說。又須結手印，以左手竪頭指，已下四指屈入",
                "賊處。上來一切作法術中，未說手印法，所以今時特說印法。以兩手中"
            ]
        }
    },
    "T1251": {
        "total": 4,
        "pages": {
            "juans/001.xhtml": 2,
            "juans/002.xhtml": 2
        },
        "sentences": {
            "juans/001.xhtml": [
                "花居。即大日如來相應天相也。手印合掌。其居座下右方與官神王，",
                "青，目白，牙上下方三寸指，正手印彼根本護身之印、左方第二手捧"
            ],
            "juans/002.xhtml": [
                "持法者現種種難惡事，即行者結手印。其鬼神縛降伏手印，兩手合掌"
            ]
        }
    },
    "T1255b": {
        "total": 1,
        "pages": {
            "juans/001.xhtml": 1
        },
        "sentences": {
            "juans/001.xhtml": [
                "金剛拳按於心上，隨誦真言以右手印於頂上左轉三匝辟除一切作障難"
            ]
        }
    },
    "T1268": {
        "total": 2,
        "pages": {
            "juans/001.xhtml": 2
        },
        "sentences": {
            "juans/001.xhtml": [
                "身印。其印陰作呪訖，先令見本手印，即知天來。解却，即手請作歡",
                "《陀羅尼集》上有此聖部真言及手印，亦取同用之，極有驗。當不得"
            ]
        }
    },
    "T1270": {
        "total": 2,
        "pages": {
            "juans/001.xhtml": 2
        },
        "sentences": {
            "juans/001.xhtml": [
                "中，自遏伽水始，一一依次第作手印取擎頂禮供養之。其手印二手作"
            ]
        }
    },
    "T1273": {
        "total": 1,
        "pages": {
            "juans/001.xhtml": 1
        },
        "sentences": {
            "juans/001.xhtml": [
                "毘那夜迦權實之義既說已。次說手印相，二手外縛，二頭指如寶形，"
            ]
        }
    },
    "T1276": {
        "total": 1,
        "pages": {
            "juans/001.xhtml": 1
        },
        "sentences": {
            "juans/001.xhtml": [
                "隨彼人後。」爾時金翅鳥王說自手印。「以二大母指相縈繞，二手如"
            ]
        }
    },
    "T1278": {
        "total": 3,
        "pages": {
            "juans/001.xhtml": 3
        },
        "sentences": {
            "juans/001.xhtml": [
                "迦樓羅心密言，密言一遍一度以手印虛撮，擲之亦得，然不知審。作",
                "，然不知審。作五大觀已，除以手印存賀字空，隨印趁之，隨手而愈",
                "，病者當起立。欲命倒者，以左手印擲向右大指中，急以右手四指握"
            ]
        }
    },
    "T1279": {
        "total": 1,
        "pages": {
            "juans/001.xhtml": 1
        },
        "sentences": {
            "juans/001.xhtml": [
                "，於左膝上坐摩登伽天。「次說手印相。二羽外相叉左押右成縛，檀"
            ]
        }
    },
    "T1291": {
        "total": 1,
        "pages": {
            "juans/001.xhtml": 1
        },
        "sentences": {
            "juans/001.xhtml": [
                "為救發遣。若欲降伏惡人者，作手印無二，以瞋心誦一百八遍，一切"
            ]
        }
    },
    "T1294": {
        "total": 1,
        "pages": {
            "juans/001.xhtml": 1
        },
        "sentences": {
            "juans/001.xhtml": [
                "時華。總著了，誦甘露真言，以手印加持，令人擎送淨處瀉於地上，"
            ]
        }
    },
    "T1315": {
        "total": 2,
        "pages": {
            "juans/001.xhtml": 2
        },
        "sentences": {
            "juans/001.xhtml": [
                "315施諸餓鬼飲食及水法(并手印)特進試鴻臚卿大興善寺三藏沙",
                "獲無量無邊福，況當來世。即作手印誦此真言加持飲食。以右手大指"
            ]
        }
    },
    "T1320": {
        "total": 3,
        "pages": {
            "juans/001.xhtml": 3
        },
        "sentences": {
            "juans/001.xhtml": [
                "，最為勝妙。依法誦此真言及作手印，如上所想供養悉皆成就。真言",
                "慢葛葛捺龕莎訶(誦之七遍。其手印相，兩手相叉合掌，以右壓左，",
                "應具此法。及奉瑜伽，皆依真言手印，持誦成就及以運心，合掌置頂"
            ]
        }
    },
    "T1338": {
        "total": 1,
        "pages": {
            "juans/001.xhtml": 1
        },
        "sentences": {
            "juans/001.xhtml": [
                "也)，所作皆成(誦呪。有身印手印，作印誦呪法即易成。若未入壇"
            ]
        }
    },
    "T1419": {
        "total": 19,
        "pages": {
            "juans/001.xhtml": 19
        },
        "sentences": {
            "juans/001.xhtml": [
                "佛著衣之相也。凡化身佛相，除手印及坐法幖幟之外，概以是作為通",
                "量壽佛之像也。凡報身佛像，除手印坐相及幖幟之外，皆以是作為通",
                "之像也。凡菩薩天男相者，除非手印坐法及幖幟之外，概以是作為通",
                "囉菩薩像凡佛母天女相者，除非手印等差別類，其餘以此式可為通用",
                "儀式(兼載須知補遺)威儀，言手印、幖幟、坐住勢及一切莊嚴也。",
                "東方金剛部主不動如來，藍色，手印於圖樣中釋迦佛手印同，謂之降",
                "。南方寶部主寶生如來，黃色，手印右手作於圖樣中救度母右手同，",
                "西方蓮華部主彌陀如來，紅色，手印同圖樣中無量壽佛，謂之禪定印",
                "北方羯磨部主不空如來，綠色，手印左手如前正定，右手胸前或乳傍",
                "中央如來部主毘嚧如來，白色，手印二拳收胸前，左拳入右拳內把之",
                "可執泥)。以上五印，略為諸佛手印之總綱(如造多佛像而不知其手印",
                "大乘法輪印，同圖樣中文殊菩薩手印(除去兩邊之華，今釋迦佛以此",
                "(除去兩邊之華，今釋迦佛以此手印造者，人多誤識為彌勒佛，因其",
                "造者，人多誤識為彌勒佛，因其手印相同故也)。又右手胸前揚掌，",
                "度所集)等經傳(化身像多用空手印，報身多用兼幖幟，然亦不可執",
                "法數(按西番十六羅漢像，俱有手印幖幟，並載公案。然總未得其梵",
                "勢，飄蕩離故鄉，所作常不利。手印幖幟錯，憂愁相纏綿，別有宜戒"
            ]
        }
    },
    "T1420": {
        "total": 2,
        "pages": {
            "juans/002.xhtml": 2
        },
        "sentences": {
            "juans/002.xhtml": [
                "雨即止。又法，取朱沙塗印，左手印人，人則歡喜。右手印人，人見"
            ]
        }
    },
    "_stat_": {
        "found_epubs": 75,
        "found_juans": 115,
        "total": 628
    }
}