{
    "T0883": {
        "total": 2,
        "pages": {
            "juans/002.xhtml": 2
        },
        "sentences": {
            "juans/002.xhtml": [
                "日月輪相，為施一切成就、一切富樂。然後令弟子著黃色衣，黃帛覆",
                "日月輪，出大光明；復現圓光顯眾色相，除諸暗冥，一切世間光明普"
            ]
        }
    },
    "T0926": {
        "total": 1,
        "pages": {
            "juans/001.xhtml": 1
        },
        "sentences": {
            "juans/001.xhtml": [
                "日月輪，無垢清淨蓮華座，於無住性願安住。諸法自性本清淨，無力"
            ]
        }
    },
    "T0957": {
        "total": 1,
        "pages": {
            "juans/001.xhtml": 1
        },
        "sentences": {
            "juans/001.xhtml": [
                "日月輪，腕表師子座，是故名如來，勝身三摩耶。當誦此密語：「o"
            ]
        }
    },
    "T0997": {
        "total": 1,
        "pages": {
            "juans/009.xhtml": 1
        },
        "sentences": {
            "juans/009.xhtml": [
                "日月輪，能令眼清淨，此寶炬總持。天眼妙清淨、慧眼無翳障、法眼"
            ]
        }
    },
    "T1067": {
        "total": 1,
        "pages": {
            "juans/001.xhtml": 1
        },
        "sentences": {
            "juans/001.xhtml": [
                "日月輪，住鉢曇摩花。次傘蓋尾曩野迦。白象頭人身，身相珂雪色，"
            ]
        }
    },
    "T1090": {
        "total": 2,
        "pages": {
            "juans/001.xhtml": 2
        },
        "sentences": {
            "juans/001.xhtml": [
                "日月輪，上想真如體，當凝然湛寂，在於月輪中。次於月輪上，復想",
                "日月輪，與前師子壇，嚴飾皆無異。上想如意輪，大蓮華如來，狀貌"
            ]
        }
    },
    "T1151": {
        "total": 1,
        "pages": {
            "juans/001.xhtml": 1
        },
        "sentences": {
            "juans/001.xhtml": [
                "日月輪，止觀金剛拳，各安於二胯，隨日作旋視，以成十方界。誦金"
            ]
        }
    },
    "T1192": {
        "total": 2,
        "pages": {
            "juans/003.xhtml": 2
        },
        "sentences": {
            "juans/003.xhtml": [
                "日月輪。於日輪上，想十二字，月輪之上，想十六字，梵字之母。出",
                "日月輪，復想唵阿吽，想於月輪上，東西而安置。從東唵阿吽，先觀"
            ]
        }
    },
    "T1193": {
        "total": 2,
        "pages": {
            "juans/001.xhtml": 2
        },
        "sentences": {
            "juans/001.xhtml": [
                "日月輪，於日輪上有十二字，月輪之上復有十六梵字之母。出生之法",
                "日月輪，復念唵阿吽，想於月輪上；又觀唵字身，化為佛輪形；復應"
            ]
        }
    },
    "_stat_": {
        "found_epubs": 9,
        "found_juans": 9,
        "total": 13
    }
}