{
    "T0885": {
        "total": 1,
        "pages": {
            "juans/003.xhtml": 1
        },
        "sentences": {
            "juans/003.xhtml": [
                "明王觀想法：「想虛空金剛，日輪曼拏羅，現焰鬘得迦，忿怒明王像"
            ]
        }
    },
    "T0891": {
        "total": 8,
        "pages": {
            "juans/001.xhtml": 8
        },
        "sentences": {
            "juans/001.xhtml": [
                "明王觀想法：「鉢囉字為大智，觀pra想鉢囉字化成無能勝大忿怒",
                "明王觀想法：「吽字為大智，觀想化成尾覲難得迦大忿hūṃ怒明王",
                "明王觀想法：「憾字為大智，觀想化為haṃ不動尊大忿怒明王，眇",
                "明王觀想法：「吽字為大智，觀想化為吒枳大hūṃ忿怒明王，三面",
                "明王觀想法：「吽字為大智，觀hūṃ想化成儞羅難拏大忿怒明王，",
                "明王觀想法：「吽字為大hūṃ智，觀想化成大力大忿怒明王，三面",
                "明王觀想法：「吽字為大智，觀想化為hūṃ送婆大忿怒明王，身大",
                "明王觀想法：「度字為大智，觀dhu想化成嚩日囉播多羅大忿怒明"
            ]
        }
    },
    "_stat_": {
        "found_epubs": 2,
        "found_juans": 2,
        "total": 9
    }
}