{
    "T0848": {
        "total": 5,
        "pages": {
            "juans/001.xhtml": 1,
            "juans/005.xhtml": 2,
            "juans/006.xhtml": 2
        },
        "sentences": {
            "juans/001.xhtml": [
                "性淨故。如是真言幻持誦成就，能生一切。復次祕密主！陽焰性空，"
            ],
            "juans/005.xhtml": [
                "聲法界語表演說如來發生偈：「能生隨類形，諸法之法相，諸佛與聲",
                "出，無量諸真言，一切戲論息，能生巧智慧。祕密主何等，一切真語"
            ],
            "juans/006.xhtml": [
                "而說偈言：「佛說真言救世者，能生一切諸真言。摩訶牟尼云何知，",
                "性空。祕密主！云何從意生？意能生影像。祕密主！譬如若白若黃若"
            ]
        }
    },
    "T0851": {
        "total": 4,
        "pages": {
            "juans/001.xhtml": 4
        },
        "sentences": {
            "juans/001.xhtml": [
                "情，令同得此地。同體大悲中，能生於鑁字，相智於臍位，白色相圓",
                "定，體同自性慧，光淨本無垢，能生於藍字，色赤如日暉，三角生威",
                "輪。次觀自性風，慧光焰鼓動，能生於唅字，形如半月輪，青黑生威",
                "魔。我畫曼荼羅，而說發生偈，能生隨類形，諸法之法相。諸佛與聲"
            ]
        }
    },
    "T0853": {
        "total": 2,
        "pages": {
            "juans/001.xhtml": 1,
            "juans/002.xhtml": 1
        },
        "sentences": {
            "juans/001.xhtml": [
                "曰(不易前指，申火相並微屈，能生大慧慈善深廣大方便)：曩莫三"
            ],
            "juans/002.xhtml": [
                "入，為華鬘也，嚴身具也。此即能生於諸佛功德，以為莊嚴法身)娑"
            ]
        }
    },
    "T0860": {
        "total": 2,
        "pages": {
            "juans/001.xhtml": 2
        },
        "sentences": {
            "juans/001.xhtml": [
                "剛座下金剛寶地所執持故。如地能生萬物，荷負一切世閒不可傾動；",
                "金剛性生，即此生者畢竟無生，能生菩提萬善，執持一切賢聖心地，"
            ]
        }
    },
    "T0863": {
        "total": 1,
        "pages": {
            "juans/001.xhtml": 1
        },
        "sentences": {
            "juans/001.xhtml": [
                "果還成種。今此阿字即同種子，能生多果，一一復生百千萬倍，乃至"
            ]
        }
    },
    "T0865": {
        "total": 2,
        "pages": {
            "juans/001.xhtml": 1,
            "juans/003.xhtml": 1
        },
        "sentences": {
            "juans/001.xhtml": [
                "哉，諸一切勝智，所離分別者，能生究竟喜。」時歡喜王大菩薩身從"
            ],
            "juans/003.xhtml": [
                "荼羅，於滿一切意願攝受無上，能生愛樂歡喜。一切如來族曼荼羅禁"
            ]
        }
    },
    "T0866": {
        "total": 2,
        "pages": {
            "juans/001.xhtml": 1,
            "juans/003.xhtml": 1
        },
        "sentences": {
            "juans/001.xhtml": [
                "切如來部壇場戒、攝取眾生事、能生無上愛喜者，怕怖畏故不入是，"
            ],
            "juans/003.xhtml": [
                "能繫留止之；由結金剛磬契故，能生歡喜。「復次，說一切如來金剛"
            ]
        }
    },
    "T0867": {
        "total": 5,
        "pages": {
            "juans/001.xhtml": 2,
            "juans/002.xhtml": 3
        },
        "sentences": {
            "juans/001.xhtml": [
                "遍，及誦本真言，能滅無量罪，能生無量福，扇底迦等法，四事速圓",
                "hūṃ吽(引)「能壞無智城，能生諸佛慧，印同妙吉祥，羯磨三昧"
            ],
            "juans/002.xhtml": [
                "，能滿一切願，能除一切不祥，能生一切福，能滅一切罪，能令一切",
                "遍，能滅一切罪。若誦滿七遍，能生無量福。若有金剛子，常持此讚",
                "子。如來常所護，能滅無等罪，能生無等福，能寂三世厄，諸佛咸衛"
            ]
        }
    },
    "T0868": {
        "total": 1,
        "pages": {
            "juans/002.xhtml": 1
        },
        "sentences": {
            "juans/002.xhtml": [
                "惱過失，成就福智，猶如虛空，能生如是最勝妙果，即是無上大菩提"
            ]
        }
    },
    "T0871": {
        "total": 2,
        "pages": {
            "juans/001.xhtml": 2
        },
        "sentences": {
            "juans/001.xhtml": [
                "哉，諸一切勝智，所離分別者，能生究竟喜。」已上金剛部四菩薩也",
                "香雲海遍周法界，見聞覺知者，能生適悅，能遍入諸佛體中，悅樂歡"
            ]
        }
    },
    "T0882": {
        "total": 5,
        "pages": {
            "juans/002.xhtml": 1,
            "juans/006.xhtml": 2,
            "juans/029.xhtml": 2
        },
        "sentences": {
            "juans/002.xhtml": [
                "一切諸勝智，若有能斷分別者，能生究竟大歡喜。」是時，極喜王大"
            ],
            "juans/006.xhtml": [
                "妙供養；鉢囉賀羅儞儞語，隨誦能生適悅心；頗羅誐摩稱誦時，隨應",
                "成就；金剛舞印供養故，諸佛尚能生妙愛；以結金剛甲冑印，乃獲金"
            ],
            "juans/029.xhtml": [
                "中觀想虛空本無自性。是中云何能生於寶？即此眾寶。又復，云何菩",
                "同生此理趣。此法若有聽聞者，能生淨信或受持，觀想常生歡喜心，"
            ]
        }
    },
    "T0884": {
        "total": 1,
        "pages": {
            "juans/001.xhtml": 1
        },
        "sentences": {
            "juans/001.xhtml": [
                "剛手！當知金剛杵即是金剛智，能生諸佛勝功德聚。金剛杵者，其相"
            ]
        }
    },
    "T0885": {
        "total": 2,
        "pages": {
            "juans/006.xhtml": 1,
            "juans/007.xhtml": 1
        },
        "sentences": {
            "juans/006.xhtml": [
                "，觀想禪定冠，三金剛三昧，不能生忿怒。」又復安住一切持大明等"
            ],
            "juans/007.xhtml": [
                "最上祕密法，若有見聞隨喜者，能生一念淨信心，所獲功德無邊際，"
            ]
        }
    },
    "T0887": {
        "total": 2,
        "pages": {
            "juans/004.xhtml": 1,
            "juans/005.xhtml": 1
        },
        "sentences": {
            "juans/004.xhtml": [
                "所生離疑怖。又想金剛薩埵生，能生禪定出生法，近成就法依本儀，"
            ],
            "juans/005.xhtml": [
                "罪皆解脫，弟子若具如是德，即能生長諸福聚。聞師言說悉無疑，所"
            ]
        }
    },
    "T0888": {
        "total": 1,
        "pages": {
            "juans/001.xhtml": 1
        },
        "sentences": {
            "juans/001.xhtml": [
                "復想大明妃！相應者持相應法；能生一切諸佛身，此是金剛界佛母！"
            ]
        }
    },
    "T0889": {
        "total": 2,
        "pages": {
            "juans/005.xhtml": 2
        },
        "sentences": {
            "juans/005.xhtml": [
                "相而能深信現大無畏，於三摩地能生金剛蓮花界佛及生種種賢聖；又",
                "有信樂現於神通。「又復真如體能生一切法，化有情身作轉輪王；復"
            ]
        }
    },
    "T0892": {
        "total": 1,
        "pages": {
            "juans/004.xhtml": 1
        },
        "sentences": {
            "juans/004.xhtml": [
                "身及餘眷屬，此諸世間所持誦處能生信愛，是故於此極生尊重，如月"
            ]
        }
    },
    "T0893a": {
        "total": 1,
        "pages": {
            "juans/002.xhtml": 1
        },
        "sentences": {
            "juans/002.xhtml": [
                "德，我今禮彼僧！諸佛同讚歎，能生種種福；號為觀自在！我今稽首"
            ]
        }
    },
    "T0893b": {
        "total": 1,
        "pages": {
            "juans/002.xhtml": 1
        },
        "sentences": {
            "juans/002.xhtml": [
                "禮。大悲觀自在！一切佛讚歎；能生種種福，我今稽首禮。大力忿怒"
            ]
        }
    },
    "T0893c": {
        "total": 1,
        "pages": {
            "juans/003.xhtml": 1
        },
        "sentences": {
            "juans/003.xhtml": [
                "禮。大悲觀自在！一切佛讚歎；能生種種福，我今稽首禮。大力忿怒"
            ]
        }
    },
    "T0894b": {
        "total": 1,
        "pages": {
            "juans/002.xhtml": 1
        },
        "sentences": {
            "juans/002.xhtml": [
                "眾生甘露解脫妙果故，慇重進修能生悉地：「為欲斷除眾生界中無量"
            ]
        }
    },
    "T0895a": {
        "total": 2,
        "pages": {
            "juans/001.xhtml": 1,
            "juans/002.xhtml": 1
        },
        "sentences": {
            "juans/001.xhtml": [
                "失利、毀謗、讚譽。此世八法，能生一切不善法故。譬如大海不宿死"
            ],
            "juans/002.xhtml": [
                "在天作耶！非無因緣，亦不從我能生諸法，但由無明流轉生死，四大"
            ]
        }
    },
    "T0895b": {
        "total": 2,
        "pages": {
            "juans/001.xhtml": 2
        },
        "sentences": {
            "juans/001.xhtml": [
                "謗、讚譽，此世八法當應遠離，能生一切不善法故。譬如大海不宿死",
                "自在之天，非無因緣，亦不從我能生諸法。但由無明流轉生死，四大"
            ]
        }
    },
    "T0905": {
        "total": 2,
        "pages": {
            "juans/001.xhtml": 2
        },
        "sentences": {
            "juans/001.xhtml": [
                "羅、波、左、那，是名出悉地，能生根莖遍滿四方，誦一遍如轉藏經",
                "尾、羅、吽、欠，是名入悉地，能生枝葉遍滿四方，光明光耀入佛法"
            ]
        }
    },
    "T0906": {
        "total": 2,
        "pages": {
            "juans/001.xhtml": 2
        },
        "sentences": {
            "juans/001.xhtml": [
                "合)，萬事通用，是名出悉地，能生根莖遍滿四方，誦一遍如轉藏經",
                "來真言中品悉地，是名入悉地。能生枝葉，又入悉地者從齊至心，遍"
            ]
        }
    },
    "T0907": {
        "total": 2,
        "pages": {
            "juans/001.xhtml": 2
        },
        "sentences": {
            "juans/001.xhtml": [
                "是下品悉地真言)是名出悉地，能生根莖遍滿四方，誦一遍如轉藏經",
                "智智金剛字句也，是名入悉地，能生枝葉遍滿四方。光明晃曜入佛法"
            ]
        }
    },
    "T0923": {
        "total": 1,
        "pages": {
            "juans/001.xhtml": 1
        },
        "sentences": {
            "juans/001.xhtml": [
                "禮。大悲觀自在，一切佛讚歎，能生種種福，我今稽首禮。大力忿怒"
            ]
        }
    },
    "T0945": {
        "total": 6,
        "pages": {
            "juans/001.xhtml": 1,
            "juans/007.xhtml": 2,
            "juans/008.xhtml": 3
        },
        "sentences": {
            "juans/001.xhtml": [
                "元清淨體，則汝今者識精元明，能生諸緣緣所遺者。由諸眾生遺此本"
            ],
            "juans/007.xhtml": [
                "持此四種律儀，皎如氷霜，自不能生一切枝葉。心三口四，生必無因",
                "以為其主，作種種形出現世時，能生眾生種種災異；有此呪地，悉皆"
            ],
            "juans/008.xhtml": [
                "。因諸愛染發起妄情，情積不休能生愛水。是故眾生心憶珍羞，口中",
                "因諸渴仰，發明虛想，想積不休能生勝氣。是故眾生心持禁戒，舉身",
                "燒觸，能為熱灰、鑪炭；燒心，能生星火迸灑，煽鼓空界。「二者、"
            ]
        }
    },
    "T0947": {
        "total": 2,
        "pages": {
            "juans/001.xhtml": 2
        },
        "sentences": {
            "juans/001.xhtml": [
                "持四種律儀皎明也。如來霜自不能生一切枝葉，心三口四生如無量因",
                "為其主，作種種形出現於世界，能生眾生種種災異。有此呪地，悉皆"
            ]
        }
    },
    "T0950": {
        "total": 8,
        "pages": {
            "juans/001.xhtml": 2,
            "juans/002.xhtml": 2,
            "juans/003.xhtml": 3,
            "juans/004.xhtml": 1
        },
        "sentences": {
            "juans/001.xhtml": [
                "輪王真言成就。祕密主！此明王能生不思議威德。「祕密主！此是如",
                "明體、光明性，與一切有情威德能生威光性。金剛手！能斷一切真言"
            ],
            "juans/002.xhtml": [
                "。』而現丈夫身。若見於女人，能生貪染心，應為不放逸，欲眠時加",
                "時，甲中停垢穢、頭髮生蟣虱，能生諸罪愆。不觀日出時、不觀日蝕"
            ],
            "juans/003.xhtml": [
                "天妙趣、名勇猛、名大勇猛、名能生、名大能生、名常、名無常、名",
                "通，流出無邊奇特，現威神力，能生一切菩薩、能摧一切俱胝魔、攝"
            ],
            "juans/004.xhtml": [
                "名指甲，是名佛慈三摩地印。「能生大慈心，住慈定行者，護持彼人"
            ]
        }
    },
    "T0951": {
        "total": 2,
        "pages": {
            "juans/002.xhtml": 1,
            "juans/003.xhtml": 1
        },
        "sentences": {
            "juans/002.xhtml": [
                "善淨法生建淨義，是二法句蔓延能生善、不善業。「是故，所食飲食"
            ],
            "juans/003.xhtml": [
                "極威德出生流布大印印呪，是中能生一切菩薩、一切證地神通大法頂"
            ]
        }
    },
    "T0952": {
        "total": 2,
        "pages": {
            "juans/002.xhtml": 1,
            "juans/003.xhtml": 1
        },
        "sentences": {
            "juans/002.xhtml": [
                "淨法生深入意，是二句法蔓延，能生善、不善業。是故，若食飲食，"
            ],
            "juans/003.xhtml": [
                "量威德出生流布大印及呪，是中能生一切菩提、能破俱胝一切魔軍、"
            ]
        }
    },
    "T0953": {
        "total": 1,
        "pages": {
            "juans/001.xhtml": 1
        },
        "sentences": {
            "juans/001.xhtml": [
                "念誦則解。如是忿怒誦摧他軍，能生一切病，令驅擯殺害枯竭迷亂狂"
            ]
        }
    },
    "T0956": {
        "total": 2,
        "pages": {
            "juans/001.xhtml": 2
        },
        "sentences": {
            "juans/001.xhtml": [
                "異。此呪亦如是，一切諸天人，能生希有心，受持及供養，所得諸功",
                "須他世界作王，即能如意捨命，能生無垢世界。「若欲成就第二死人"
            ]
        }
    },
    "T0975": {
        "total": 1,
        "pages": {
            "juans/001.xhtml": 1
        },
        "sentences": {
            "juans/001.xhtml": [
                "光神通，緣出無邊奇特大威神，能生一切菩薩，能摧一切俱低魔眾，"
            ]
        }
    },
    "T0994": {
        "total": 3,
        "pages": {
            "juans/001.xhtml": 3
        },
        "sentences": {
            "juans/001.xhtml": [
                "不生故。然此阿字是一切字母，能生一切字。若得阿字門瑜伽相應，",
                "云覺心)散惹(引)曩儞(此云能生，順此方言，即前三世圓成能生"
            ]
        }
    },
    "T0996": {
        "total": 4,
        "pages": {
            "juans/001.xhtml": 4
        },
        "sentences": {
            "juans/001.xhtml": [
                "本不生故。婀字是一切字之母，能生一切法。若能曉婀字門瑜伽相應",
                "法。冒地質多散惹娜儞。顯句釋能生菩提心義，密句釋冒字一字為種",
                "平等，前剎那後剎那一相清淨，能生一切波羅蜜一切地，即名般若佛",
                "顯教，觀行般若作為生因顯因，能生一切佛菩薩，是故名佛母。從前"
            ]
        }
    },
    "T0997": {
        "total": 16,
        "pages": {
            "juans/001.xhtml": 6,
            "juans/002.xhtml": 1,
            "juans/006.xhtml": 3,
            "juans/008.xhtml": 2,
            "juans/009.xhtml": 1,
            "juans/010.xhtml": 3
        },
        "sentences": {
            "juans/001.xhtml": [
                "慧深廣，無量無邊、無能至底，能生一切功德寶聚，猶如大海；普雨",
                "歡喜難自持。我讚如來世間燈，能生功德最勝智，以此福聚利含識，",
                "外道境界，微妙寂靜不可思議，能生諸佛無等等智不可思議，流出法",
                "聲、隨其所樂聞種種法、隨其力能生種種解。雖隨眾生如是知見，而",
                "根安靜。其聲深遠，諦實清徹，能生善根，文字名句悉皆具足，與義",
                "波羅蜜聲、清淨尸羅波羅蜜聲、能生羼提波羅蜜聲、勤修精進波羅蜜"
            ],
            "juans/002.xhtml": [
                "暫修習此三昧者，身心輕安，即能生於五種三昧。何等為五？一者、"
            ],
            "juans/006.xhtml": [
                "下劣聲、無堅硬聲、無慢緩聲、能生安樂聲、令身清淨聲、令心歡喜",
                "甚深聲、無厭聲、令耳安樂聲、能生善根聲、字句圓滿聲、妙詞句字",
                "聲、莊嚴布施聲、能持淨戒聲、能生安忍聲、猛利精進聲、堪任靜慮"
            ],
            "juans/008.xhtml": [
                "，皆稱根性令其歡喜，於未來世能生菩薩一切善根，能令一切初發心",
                "分別解說。「善男子！般若根本能生般若即般若母，般若事業即是所"
            ],
            "juans/009.xhtml": [
                "、唵字即是一切陀羅尼母，從此能生一切如來，從如來生一切菩薩，"
            ],
            "juans/010.xhtml": [
                "門、能超出三界、能善覺三智、能生如來金剛三昧，是一切法之所住",
                "此深經，最勝福聚悉皆圓，從此能生於善逝。若世無此勝經寶，佛種",
                "、聲聞緣覺得菩提，此經一切悉能生，如摩尼寶隨心願。」爾時，世"
            ]
        }
    },
    "T1005A": {
        "total": 1,
        "pages": {
            "juans/001.xhtml": 1
        },
        "sentences": {
            "juans/001.xhtml": [
                "能息一切怖畏、能滅一切惡障、能生一切功德、能成就六波羅蜜、能成"
            ]
        }
    },
    "T1006": {
        "total": 2,
        "pages": {
            "juans/001.xhtml": 2
        },
        "sentences": {
            "juans/001.xhtml": [
                "此眾生不能得聞、不能受持、不能生敬。此陀羅尼能滅一切罪，是諸",
                "能除一切怖畏，能滅一切惡障，能生一切功德，能成就六波羅蜜，成"
            ]
        }
    },
    "T1024": {
        "total": 1,
        "pages": {
            "juans/001.xhtml": 1
        },
        "sentences": {
            "juans/001.xhtml": [
                "「世尊！何者是彼陀羅尼法，而能生長福德善根？」佛言：「有大陀"
            ]
        }
    },
    "T1025": {
        "total": 1,
        "pages": {
            "juans/002.xhtml": 1
        },
        "sentences": {
            "juans/002.xhtml": [
                "旋遶一百八遍，能滅一切惡業、能生一切善種。天主！若欲安置此心"
            ]
        }
    },
    "T1079": {
        "total": 1,
        "pages": {
            "juans/001.xhtml": 1
        },
        "sentences": {
            "juans/001.xhtml": [
                "，移須彌山及大海水，呪乾枯木能生華菓。若常誦持，水不能溺火不"
            ]
        }
    },
    "T1092": {
        "total": 2,
        "pages": {
            "juans/001.xhtml": 1,
            "juans/003.xhtml": 1
        },
        "sentences": {
            "juans/001.xhtml": [
                "通，亦不能救。世尊！如斯有情能生悔心，清潔澡浴，以香塗身，著"
            ],
            "juans/003.xhtml": [
                "胝劫受劇苦。如斯罪累等有情，能生怖心悔眾罪，若得見聞此經典，"
            ]
        }
    },
    "T1094": {
        "total": 1,
        "pages": {
            "juans/001.xhtml": 1
        },
        "sentences": {
            "juans/001.xhtml": [
                "而不能救。彼若聞此神呪心經，能生悔愧終不更造，若彼復能經一日"
            ]
        }
    },
    "T1096": {
        "total": 1,
        "pages": {
            "juans/001.xhtml": 1
        },
        "sentences": {
            "juans/001.xhtml": [
                "無量福德資糧、增長善根，皆悉能生無邊智慧，神通境界超過得入，"
            ]
        }
    },
    "T1098": {
        "total": 1,
        "pages": {
            "juans/001.xhtml": 1
        },
        "sentences": {
            "juans/001.xhtml": [
                "神通亦不能救。世尊！如斯有情能生悔心，清潔澡浴、以香塗身、著"
            ]
        }
    },
    "T1103b": {
        "total": 2,
        "pages": {
            "juans/001.xhtml": 2
        },
        "sentences": {
            "juans/001.xhtml": [
                "量無邊福德資糧積集善根增長，能生無量無邊智慧神通境界，能超過",
                "得作佛。不可思議。世人聞此未能生信，恐有生謗，不欲流傳。同修"
            ]
        }
    },
    "T1153": {
        "total": 1,
        "pages": {
            "juans/002.xhtml": 1
        },
        "sentences": {
            "juans/002.xhtml": [
                "諸罪，大力勇健具大威德神力，能生無量功德，能摧一切魔眾，能斷"
            ]
        }
    },
    "T1159B": {
        "total": 4,
        "pages": {
            "juans/001.xhtml": 4
        },
        "sentences": {
            "juans/001.xhtml": [
                "，亦如寶濖一切商人，亦如大地能生善根，亦是涅槃求法神器，亦是",
                "報，清淨第一堅固不壞，妙色處能生受樂，於大會處而生慚愧，除諸",
                "最勝大導師，恒修於慈發善心，能生忍辱如大地，解脫眾生除瞋恚。",
                "欲度濁惡世，成就一切諸眾生。能生堅固懃精進，超過無量諸苦行，"
            ]
        }
    },
    "T1167": {
        "total": 1,
        "pages": {
            "juans/001.xhtml": 1
        },
        "sentences": {
            "juans/001.xhtml": [
                "障，是故我頂禮，無盡智慧尊，能生無竭辯。如地諸有情，所依一不"
            ]
        }
    },
    "T1168B": {
        "total": 1,
        "pages": {
            "juans/001.xhtml": 1
        },
        "sentences": {
            "juans/001.xhtml": [
                "aṃkula多諸眾生令得安樂能生眾putravahujana"
            ]
        }
    },
    "T1169": {
        "total": 1,
        "pages": {
            "juans/004.xhtml": 1
        },
        "sentences": {
            "juans/004.xhtml": [
                "熾焰遍身，坐白蓮花，而於身中能生諸佛。若觀字成多羅菩薩者，身"
            ]
        }
    },
    "T1177A": {
        "total": 1,
        "pages": {
            "juans/007.xhtml": 1
        },
        "sentences": {
            "juans/007.xhtml": [
                "提故。十者慧心，於一切智慧，能生一切佛法，般若波羅蜜多是名慧"
            ]
        }
    },
    "T1189": {
        "total": 1,
        "pages": {
            "juans/001.xhtml": 1
        },
        "sentences": {
            "juans/001.xhtml": [
                "剛稱及心。大幻金剛腹，金剛主能生，金剛藏虛空，不動一髻尊，身"
            ]
        }
    },
    "T1190": {
        "total": 1,
        "pages": {
            "juans/001.xhtml": 1
        },
        "sentences": {
            "juans/001.xhtml": [
                "，真實斷除一切業障無有遺餘，能生一切相續八難者令其不生，能滅"
            ]
        }
    },
    "T1191": {
        "total": 3,
        "pages": {
            "juans/007.xhtml": 1,
            "juans/013.xhtml": 1,
            "juans/018.xhtml": 1
        },
        "sentences": {
            "juans/007.xhtml": [
                "彼菩提種子。譬如鹹鹵之地，不能生於百穀之苗集其種子。信為萬善"
            ],
            "juans/013.xhtml": [
                "如盲聾人不見不聞，設遇聞見不能生信，如是之事說不可盡。又復如"
            ],
            "juans/018.xhtml": [
                "專心無二稟信奉行，於一生中亦能生彼。而此真言如佛所說，一切愚"
            ]
        }
    },
    "T1201": {
        "total": 1,
        "pages": {
            "juans/002.xhtml": 1
        },
        "sentences": {
            "juans/002.xhtml": [
                "伽伽那劍莎縛訶」持此明力故，能生如意寶，供養一切諸佛菩薩眾會"
            ]
        }
    },
    "T1251": {
        "total": 1,
        "pages": {
            "juans/003.xhtml": 1
        },
        "sentences": {
            "juans/003.xhtml": [
                "悉供養，皆共稱歎可歸依，眾德能生能念示，一切時中起恭敬。是故"
            ]
        }
    },
    "T1257": {
        "total": 1,
        "pages": {
            "juans/001.xhtml": 1
        },
        "sentences": {
            "juans/001.xhtml": [
                "心](切身)摩木作護摩一千，能生冤家病。若以自身血、芥子、油"
            ]
        }
    },
    "T1300": {
        "total": 1,
        "pages": {
            "juans/001.xhtml": 1
        },
        "sentences": {
            "juans/001.xhtml": [
                "有五祠法，言斯祠者是涅槃因，能生天上。何者為五？一殺害人取脂"
            ]
        }
    },
    "T1332": {
        "total": 3,
        "pages": {
            "juans/001.xhtml": 2,
            "juans/003.xhtml": 1
        },
        "sentences": {
            "juans/001.xhtml": [
                "無上陀羅尼。是故當好持戒，戒能生定，定能生慧。」第一文殊師利"
            ],
            "juans/003.xhtml": [
                "普雨法雨無不蒙益，枯木石山皆能生華，強者能伏弱者能佐。作是念"
            ]
        }
    },
    "T1334": {
        "total": 1,
        "pages": {
            "juans/001.xhtml": 1
        },
        "sentences": {
            "juans/001.xhtml": [
                "者，於未來世末劫之中建立三寶能生正信。若比丘、比丘尼、優婆塞"
            ]
        }
    },
    "T1336": {
        "total": 1,
        "pages": {
            "juans/003.xhtml": 1
        },
        "sentences": {
            "juans/003.xhtml": [
                "普雨法雨無不蒙益，枯木石山皆能生華，強者能伏、弱者能佐。作是"
            ]
        }
    },
    "T1340": {
        "total": 11,
        "pages": {
            "juans/003.xhtml": 1,
            "juans/004.xhtml": 1,
            "juans/006.xhtml": 1,
            "juans/007.xhtml": 1,
            "juans/008.xhtml": 2,
            "juans/009.xhtml": 1,
            "juans/010.xhtml": 1,
            "juans/012.xhtml": 3
        },
        "sentences": {
            "juans/003.xhtml": [
                "事故。其禪波羅蜜者，此中總說能生六波羅蜜故。摩那婆！此諸波羅"
            ],
            "juans/004.xhtml": [
                "大涅槃路，為諸菩薩證三菩提，能生種種順義精進，能滿智慧所作業"
            ],
            "juans/006.xhtml": [
                "藏不生信解，假使更聞諸餘法相能生信者，無有是處。當知是人去佛"
            ],
            "juans/007.xhtml": [
                "能知，況我更說深密勝法，云何能生真實定慧也？摩那婆！所有法數"
            ],
            "juans/008.xhtml": [
                "者，是中何者是阿字？何者是聲能生字？何者是聲生來處？摩那婆！",
                "，頗復有人能思量不？恐亦無有能生信人，唯有如來乃能知耳。或時"
            ],
            "juans/009.xhtml": [
                "。摩那婆！若諸眾生聞是深法，能生信解正念思惟，如是之人諸佛菩"
            ],
            "juans/010.xhtml": [
                "，或於過去諸如來所聞是法門亦能生信。摩那婆！汝等諦聽，我當為"
            ],
            "juans/012.xhtml": [
                "言：『世尊！斯諸菩薩從何處所能生是智，知見往昔十四億數諸如來",
                "稱量。如彼地界頑礙無邊，是中能生種種草木枝葉華果，復有種種寶",
                "：『憍尸迦！汝先所問何等三昧能生智業者，憍尸迦！復有三昧名建"
            ]
        }
    },
    "T1341": {
        "total": 13,
        "pages": {
            "juans/001.xhtml": 2,
            "juans/002.xhtml": 1,
            "juans/004.xhtml": 1,
            "juans/006.xhtml": 2,
            "juans/010.xhtml": 3,
            "juans/012.xhtml": 1,
            "juans/013.xhtml": 1,
            "juans/014.xhtml": 1,
            "juans/017.xhtml": 1
        },
        "sentences": {
            "juans/001.xhtml": [
                "法具足捨佛菩提。比丘五法具足能生瞋恚，瞋恚生已捨佛語。俗人五",
                "怖死，死已不假作念知所生處，能生厭離而不放逸。七十五種相具足"
            ],
            "juans/002.xhtml": [
                "負苦重、食糞噉穢，多有鬪諍不能生忍，烏鳥啄蹋為人所乘，脚行繚"
            ],
            "juans/004.xhtml": [
                "名心思量，生諸法耶？緣境思念能生增長，以是義故，名心思生法。"
            ],
            "juans/006.xhtml": [
                "邊生實想者，彼諸眾生於諸法中能生歡喜信敬之心。諸法能生歡喜信"
            ],
            "juans/010.xhtml": [
                "是為五不喜想。於中此等諸想中能生不喜樂者，唯有一想。何者一想",
                "不喜樂者，唯有一想。何者一想能生？所謂於諸法中不生敬重。以不",
                "是甚深佛菩提中不作恐怖。彼等能生實想，於是法中當度彼岸，彼等"
            ],
            "juans/012.xhtml": [
                "一劫，彼亦不曾生於身想，況復能生團食想也。何以故？此凡夫輩攝"
            ],
            "juans/013.xhtml": [
                "如是。阿難！無分別住處，豈可能生不正念分別也？」「不也。世尊"
            ],
            "juans/014.xhtml": [
                "信已復信。一切煩惱愛為根本，能生一切憂愁啼哭一切諸苦，是故言"
            ],
            "juans/017.xhtml": [
                "能覺知，唯除如來也。五法具足能生食愛，阿耶吒陀耶波梨拏摩多夜"
            ]
        }
    },
    "T1344": {
        "total": 2,
        "pages": {
            "juans/001.xhtml": 2
        },
        "sentences": {
            "juans/001.xhtml": [
                "尼門。何以故？文殊師利！愛是能生煩惱因故。文殊師利！於意云何",
                "欲。文殊師利！於汝意云何？色能生聲不？」文殊師利言：「不也。"
            ]
        }
    },
    "T1345": {
        "total": 1,
        "pages": {
            "juans/001.xhtml": 1
        },
        "sentences": {
            "juans/001.xhtml": [
                "？云何名癡？諸法本來解脫，以能生惱故名為癡。諸法本來解脫，無"
            ]
        }
    },
    "T1361": {
        "total": 6,
        "pages": {
            "juans/001.xhtml": 6
        },
        "sentences": {
            "juans/001.xhtml": [
                "雜染；三、與不清淨因麁重之果能生之力而不隨順；四、而能斷除彼",
                "波羅蜜多若有圓滿，唯清淨心不能生長無上智果，是故說彼名為波羅",
                "。論曰「三與不清淨因麁重之果能生之力而不隨順」者，此是第三，",
                "即此名為處不淨因，彼處自果。能生力者，謂能引其等流異熟之果力",
                "波羅蜜多若不圓滿，唯清淨心不能生長無上智果，是故說彼名為波羅",
                "金剛喻定。彼亦而從資糧圓滿乃能生長，非從餘得。論曰「六盡諸世"
            ]
        }
    },
    "T1374": {
        "total": 2,
        "pages": {
            "juans/001.xhtml": 2
        },
        "sentences": {
            "juans/001.xhtml": [
                "佛言：「善哉善哉！汝護正法，能生如是殷重之心。」爾時持國天王",
                "等所害。若有信經書寫人，供養能生無量福，一切眾生智如佛，多劫"
            ]
        }
    },
    "T1420": {
        "total": 1,
        "pages": {
            "juans/002.xhtml": 1
        },
        "sentences": {
            "juans/002.xhtml": [
                "得者，甚令祕之，實莫妄傳。若能生信恭養敬求覓者，看其行恤，然"
            ]
        }
    },
    "_stat_": {
        "found_epubs": 71,
        "found_juans": 113,
        "total": 174
    }
}