{
    "T0889": {
        "total": 1,
        "pages": {
            "juans/002.xhtml": 1
        },
        "sentences": {
            "juans/002.xhtml": [
                "印而警覺之，既覺悟已復放光明，為圓滿一切智智。」佛言：「所觀月輪三昧印心相善界，即是本尊如來種子之智。「復次，眾生之心住"
            ]
        }
    },
    "T0997": {
        "total": 4,
        "pages": {
            "juans/002.xhtml": 3,
            "juans/009.xhtml": 1
        },
        "sentences": {
            "juans/002.xhtml": [
                "曰：「唵吽惹護(平)娑」「云何觀察此陀羅尼？當以唵字安前所觀月輪之中，置於頂上，觀此唵字色如珂雪。此想成已，即見自身坐月",
                "昧，四者、起伏三昧，五者、安住三昧。「云何名為剎那三昧？謂觀月輪剎那剎那暫持相應尋復還失，是故名為剎那三昧。「云何名為微",
                "漸增勝，身毛皆竪，悲泣流淚。如黑物中見一白縷，此亦如是，由觀月輪得少分住，於無明闇煩惱之中見少定心微分顯現。「云何名為起"
            ],
            "juans/009.xhtml": [
                "端繫想。為除煩惱等，增長三摩提，當想於本尊，護摩勤念誦。先觀月輪淨，想自坐輪中，發焰光熾然，天光嚴自體。十方現在佛，五色"
            ]
        }
    },
    "T1092": {
        "total": 1,
        "pages": {
            "juans/007.xhtml": 1
        },
        "sentences": {
            "juans/007.xhtml": [
                "。觀置風輪上有水輪，色猶雪乳，中有縛字若塞頗胝，皎月光淨。觀月輪上有大目陀羅金剛輪曼拏羅，放金光焰，上觀縒字變為八葉自開"
            ]
        }
    },
    "_stat_": {
        "found_epubs": 3,
        "found_juans": 4,
        "total": 6
    }
}