{
    "T0885": {
        "total": 1,
        "pages": {
            "juans/002.xhtml": 1
        },
        "sentences": {
            "juans/002.xhtml": [
                "佛最勝身語心。「所謂唵字即諸佛最勝身，唵阿字即諸佛真實語，阿吽字即諸佛大智心。「又復，吽字亦即無上菩提，此即一切如來無上"
            ]
        }
    },
    "T0892": {
        "total": 3,
        "pages": {
            "juans/001.xhtml": 1,
            "juans/003.xhtml": 1,
            "juans/005.xhtml": 1
        },
        "sentences": {
            "juans/001.xhtml": [
                "熾盛威儀真言品第二「施一切地上飲食真言曰：「唵(引)(一)阿吽(引)(三)發吒(半音)莎(引)賀(引下同)(四)」佛言："
            ],
            "juans/003.xhtml": [
                "引)薩嚩(二合)訶「唵(引)嚩日囉(二合)禰(引)閉(引)阿吽(引)薩嚩(二合)訶「唵(引)嚩日囉(二合)喭提阿(引)吽"
            ],
            "juans/005.xhtml": [
                "相即四明妃。「七等覺支及四真諦所生諸八部真言曰：「唵(引)阿吽(引)發吒(半音)薩嚩(二合引)賀」持念品第十九「復次，金"
            ]
        }
    },
    "T1091": {
        "total": 1,
        "pages": {
            "juans/001.xhtml": 1
        },
        "sentences": {
            "juans/001.xhtml": [
                "帝遮揭阿沙吽唎婆訶(十二)唵(十三)波地迷真多摩尼摩訶遮揭阿吽(十四)唵波阿多波地迷吽(十五)」七星本部印如意輪本印長誦"
            ]
        }
    },
    "T1192": {
        "total": 2,
        "pages": {
            "juans/003.xhtml": 2
        },
        "sentences": {
            "juans/003.xhtml": [
                "色，東白南青色，西紅北金色。想於其壇中，而有日月輪，復想唵阿吽，想於月輪上，東西而安置。從東唵阿吽，先觀唵字體，想為八菩"
            ]
        }
    },
    "T1193": {
        "total": 1,
        "pages": {
            "juans/001.xhtml": 1
        },
        "sentences": {
            "juans/001.xhtml": [
                "色，東白南青色，西黃北金色。想於其閣中，而有日月輪，復念唵阿吽，想於月輪上；又觀唵字身，化為佛輪形；復應想阿字，而成寶蓮"
            ]
        }
    },
    "T1251": {
        "total": 1,
        "pages": {
            "juans/003.xhtml": 1
        },
        "sentences": {
            "juans/003.xhtml": [
                "、面各三遍。指固印捧首，如天衣結垂莊嚴。真言曰：「唵跋折羅阿吽(二合)」「次作定印，念八界成竟，次我所成界自身召入印。二"
            ]
        }
    },
    "T1418": {
        "total": 1,
        "pages": {
            "juans/001.xhtml": 1
        },
        "sentences": {
            "juans/001.xhtml": [
                "(二合)賀」「誦此真言已，復想如來如真實身諸相圓滿，然以唵阿吽三字安在像身三處，用唵字安頂上、用阿字安口上、用吽字安心上"
            ]
        }
    },
    "_stat_": {
        "found_epubs": 7,
        "found_juans": 9,
        "total": 10
    }
}